[
  {
    "ticker": "ULYX",
    "isin": null,
    "company_name": "Urgent.ly Inc.  (ULYX)",
    "market_cap_mm": null,
    "signal_type": "activist_keyword",
    "signal_category": "edgar",
    "strength_estimate": 2,
    "source_url": "https://www.sec.gov/Archives/edgar/data/1603652/000119312526161739",
    "source_date": "2026-04-17",
    "scan_date": "2026-04-17",
    "raw_data": {
      "keyword": "strategic alternatives",
      "filing_type": "SC 14D9/A",
      "cik": "0001603652",
      "adsh": "0001193125-26-161739",
      "file_description": "SC 14D9/A",
      "company_raw": "Urgent.ly Inc.  (ULYX)  (CIK 0001603652)"
    }
  },
  {
    "ticker": "SOWG",
    "isin": null,
    "company_name": "Sow Good Inc.  (SOWG)",
    "market_cap_mm": null,
    "signal_type": "activist_keyword",
    "signal_category": "edgar",
    "strength_estimate": 2,
    "source_url": "https://www.sec.gov/Archives/edgar/data/1490161/000182912626003615",
    "source_date": "2026-04-17",
    "scan_date": "2026-04-17",
    "raw_data": {
      "keyword": "strategic alternatives",
      "filing_type": "8-K",
      "cik": "0001490161",
      "adsh": "0001829126-26-003615",
      "file_description": "EXHIBIT 99.1",
      "company_raw": "Sow Good Inc.  (SOWG)  (CIK 0001490161)"
    }
  },
  {
    "ticker": "GPUS",
    "isin": null,
    "company_name": "Hyperscale Data, Inc.  (GPUS, GPUS-PD)",
    "market_cap_mm": null,
    "signal_type": "activist_keyword",
    "signal_category": "edgar",
    "strength_estimate": 2,
    "source_url": "https://www.sec.gov/Archives/edgar/data/896493/000121465926004810",
    "source_date": "2026-04-17",
    "scan_date": "2026-04-17",
    "raw_data": {
      "keyword": "undervalued",
      "filing_type": "8-K",
      "cik": "0000896493",
      "adsh": "0001214659-26-004810",
      "file_description": "EXHIBIT 99.2",
      "company_raw": "Hyperscale Data, Inc.  (GPUS, GPUS-PD)  (CIK 0000896493)"
    }
  },
  {
    "ticker": "MAIR",
    "isin": null,
    "company_name": "Madison Air Solutions Corp  (MAIR)",
    "market_cap_mm": null,
    "signal_type": "activist_keyword",
    "signal_category": "edgar",
    "strength_estimate": 2,
    "source_url": "https://www.sec.gov/Archives/edgar/data/2098430/000119312526161509",
    "source_date": "2026-04-17",
    "scan_date": "2026-04-17",
    "raw_data": {
      "keyword": "consent solicitation",
      "filing_type": "8-K",
      "cik": "0002098430",
      "adsh": "0001193125-26-161509",
      "file_description": "EX-3.1",
      "company_raw": "Madison Air Solutions Corp  (MAIR)  (CIK 0002098430)"
    }
  },
  {
    "ticker": "TE",
    "isin": null,
    "company_name": "T1 Energy Inc.  (TE, TE-WT)",
    "market_cap_mm": null,
    "signal_type": "activist_keyword",
    "signal_category": "edgar",
    "strength_estimate": 2,
    "source_url": "https://www.sec.gov/Archives/edgar/data/1992243/000121390026045173",
    "source_date": "2026-04-17",
    "scan_date": "2026-04-17",
    "raw_data": {
      "keyword": "consent solicitation",
      "filing_type": "8-K",
      "cik": "0001992243",
      "adsh": "0001213900-26-045173",
      "file_description": "SECOND SUPPLEMENTAL INDENTURE",
      "company_raw": "T1 Energy Inc.  (TE, TE-WT)  (CIK 0001992243)"
    }
  },
  {
    "ticker": "SOAR",
    "isin": null,
    "company_name": "Volato Group, Inc.  (SOAR, SOARW)",
    "market_cap_mm": null,
    "signal_type": "distress_keyword",
    "signal_category": "edgar",
    "strength_estimate": 4,
    "source_url": "https://www.sec.gov/Archives/edgar/data/1853070/000149315226017829",
    "source_date": "2026-04-17",
    "scan_date": "2026-04-17",
    "raw_data": {
      "keyword": "going concern",
      "filing_type": "8-K",
      "cik": "0001853070",
      "adsh": "0001493152-26-017829",
      "file_description": "8-K",
      "company_raw": "Volato Group, Inc.  (SOAR, SOARW)  (CIK 0001853070)"
    }
  },
  {
    "ticker": "BRLS",
    "isin": null,
    "company_name": "Borealis Foods Inc.  (BRLS, BRLSW)",
    "market_cap_mm": null,
    "signal_type": "distress_keyword",
    "signal_category": "edgar",
    "strength_estimate": 2,
    "source_url": "https://www.sec.gov/Archives/edgar/data/1852973/000121390026045167",
    "source_date": "2026-04-17",
    "scan_date": "2026-04-17",
    "raw_data": {
      "keyword": "forbearance agreement",
      "filing_type": "8-K",
      "cik": "0001852973",
      "adsh": "0001213900-26-045167",
      "file_description": "NOTICE OF FORBEARANCE DEFAULT, DATED APRIL 13, 2026, FROM FRONTWELL CAPITAL PARTNERS INC. TO BOREALIS FOODS INC",
      "company_raw": "Borealis Foods Inc.  (BRLS, BRLSW)  (CIK 0001852973)"
    }
  },
  {
    "ticker": "TDG",
    "isin": null,
    "company_name": "TransDigm Group INC  (TDG)",
    "market_cap_mm": null,
    "signal_type": "distress_keyword",
    "signal_category": "edgar",
    "strength_estimate": 2,
    "source_url": "https://www.sec.gov/Archives/edgar/data/1260221/000119312526161564",
    "source_date": "2026-04-17",
    "scan_date": "2026-04-17",
    "raw_data": {
      "keyword": "restatement",
      "filing_type": "8-K",
      "cik": "0001260221",
      "adsh": "0001193125-26-161564",
      "file_description": "EX-10.1",
      "company_raw": "TransDigm Group INC  (TDG)  (CIK 0001260221)"
    }
  },
  {
    "ticker": "ARXS",
    "isin": null,
    "company_name": "Arxis, Inc.  (ARXS)",
    "market_cap_mm": null,
    "signal_type": "distress_keyword",
    "signal_category": "edgar",
    "strength_estimate": 2,
    "source_url": "https://www.sec.gov/Archives/edgar/data/2093536/000119312526161805",
    "source_date": "2026-04-17",
    "scan_date": "2026-04-17",
    "raw_data": {
      "keyword": "restatement",
      "filing_type": "8-K",
      "cik": "0002093536",
      "adsh": "0001193125-26-161805",
      "file_description": "8-K",
      "company_raw": "Arxis, Inc.  (ARXS)  (CIK 0002093536)"
    }
  },
  {
    "ticker": "HGTXU",
    "isin": null,
    "company_name": "HUGOTON ROYALTY TRUST  (HGTXU)",
    "market_cap_mm": null,
    "signal_type": "distress_keyword",
    "signal_category": "edgar",
    "strength_estimate": 4,
    "source_url": "https://www.sec.gov/Archives/edgar/data/862022/000119312526161712",
    "source_date": "2026-04-17",
    "scan_date": "2026-04-17",
    "raw_data": {
      "keyword": "substantial doubt",
      "filing_type": "8-K",
      "cik": "0000862022",
      "adsh": "0001193125-26-161712",
      "file_description": "8-K",
      "company_raw": "HUGOTON ROYALTY TRUST  (HGTXU)  (CIK 0000862022)"
    }
  },
  {
    "ticker": "BAM",
    "isin": null,
    "company_name": "Brookfield Asset Management Ltd.  (BAM)",
    "market_cap_mm": null,
    "signal_type": "mna_keyword",
    "signal_category": "edgar",
    "strength_estimate": 3,
    "source_url": "https://www.sec.gov/Archives/edgar/data/1937926/000110465926044893",
    "source_date": "2026-04-17",
    "scan_date": "2026-04-17",
    "raw_data": {
      "keyword": "change of control",
      "filing_type": "8-K",
      "cik": "0001937926",
      "adsh": "0001104659-26-044893",
      "file_description": "EXHIBIT 4.4",
      "company_raw": "Brookfield Asset Management Ltd.  (BAM)  (CIK 0001937926)"
    }
  },
  {
    "ticker": "TGNT",
    "isin": null,
    "company_name": "Totaligent, Inc.  (TGNT)",
    "market_cap_mm": null,
    "signal_type": "mna_keyword",
    "signal_category": "edgar",
    "strength_estimate": 5,
    "source_url": "https://www.sec.gov/Archives/edgar/data/846377/000147793226002227",
    "source_date": "2026-04-15",
    "scan_date": "2026-04-17",
    "raw_data": {
      "keyword": "definitive agreement",
      "filing_type": "8-K",
      "cik": "0000846377",
      "adsh": "0001477932-26-002227",
      "file_description": "FORM 8-K",
      "company_raw": "Totaligent, Inc.  (TGNT)  (CIK 0000846377)"
    }
  },
  {
    "ticker": "ARQ",
    "isin": null,
    "company_name": "Arq, Inc.  (ARQ)",
    "market_cap_mm": null,
    "signal_type": "mna_keyword",
    "signal_category": "edgar",
    "strength_estimate": 5,
    "source_url": "https://www.sec.gov/Archives/edgar/data/1515156/000151515626000045",
    "source_date": "2026-04-17",
    "scan_date": "2026-04-17",
    "raw_data": {
      "keyword": "definitive agreement",
      "filing_type": "8-K",
      "cik": "0001515156",
      "adsh": "0001515156-26-000045",
      "file_description": "8-K",
      "company_raw": "Arq, Inc.  (ARQ)  (CIK 0001515156)"
    }
  },
  {
    "ticker": "FMBH",
    "isin": null,
    "company_name": "FIRST MID BANCSHARES, INC.  (FMBH)",
    "market_cap_mm": null,
    "signal_type": "mna_keyword",
    "signal_category": "edgar",
    "strength_estimate": 5,
    "source_url": "https://www.sec.gov/Archives/edgar/data/700565/000117184326002468",
    "source_date": "2026-04-15",
    "scan_date": "2026-04-17",
    "raw_data": {
      "keyword": "definitive agreement",
      "filing_type": "8-K",
      "cik": "0000700565",
      "adsh": "0001171843-26-002468",
      "file_description": "FORM 8-K",
      "company_raw": "FIRST MID BANCSHARES, INC.  (FMBH)  (CIK 0000700565)"
    }
  },
  {
    "ticker": "FLS",
    "isin": null,
    "company_name": "FLOWSERVE CORP  (FLS)",
    "market_cap_mm": null,
    "signal_type": "mna_keyword",
    "signal_category": "edgar",
    "strength_estimate": 5,
    "source_url": "https://www.sec.gov/Archives/edgar/data/30625/000119312526156982",
    "source_date": "2026-04-15",
    "scan_date": "2026-04-17",
    "raw_data": {
      "keyword": "definitive agreement",
      "filing_type": "8-K",
      "cik": "0000030625",
      "adsh": "0001193125-26-156982",
      "file_description": "8-K",
      "company_raw": "FLOWSERVE CORP  (FLS)  (CIK 0000030625)"
    }
  },
  {
    "ticker": "OPFI",
    "isin": null,
    "company_name": "OppFi Inc.  (OPFI, OPFI-WT)",
    "market_cap_mm": null,
    "signal_type": "mna_keyword",
    "signal_category": "edgar",
    "strength_estimate": 5,
    "source_url": "https://www.sec.gov/Archives/edgar/data/1818502/000181850226000023",
    "source_date": "2026-04-16",
    "scan_date": "2026-04-17",
    "raw_data": {
      "keyword": "definitive agreement",
      "filing_type": "8-K",
      "cik": "0001818502",
      "adsh": "0001818502-26-000023",
      "file_description": "8-K",
      "company_raw": "OppFi Inc.  (OPFI, OPFI-WT)  (CIK 0001818502)"
    }
  },
  {
    "ticker": "BMI",
    "isin": null,
    "company_name": "BADGER METER INC  (BMI)",
    "market_cap_mm": null,
    "signal_type": "mna_keyword",
    "signal_category": "edgar",
    "strength_estimate": 5,
    "source_url": "https://www.sec.gov/Archives/edgar/data/9092/000119312526160389",
    "source_date": "2026-04-17",
    "scan_date": "2026-04-17",
    "raw_data": {
      "keyword": "definitive agreement",
      "filing_type": "8-K",
      "cik": "0000009092",
      "adsh": "0001193125-26-160389",
      "file_description": "EX-99.PRESSRELEASE",
      "company_raw": "BADGER METER INC  (BMI)  (CIK 0000009092)"
    }
  },
  {
    "ticker": "ASBP",
    "isin": null,
    "company_name": "Aspire Biopharma Holdings, Inc.  (ASBP, ASBPW)",
    "market_cap_mm": null,
    "signal_type": "mna_keyword",
    "signal_category": "edgar",
    "strength_estimate": 5,
    "source_url": "https://www.sec.gov/Archives/edgar/data/1847345/000149315226016979",
    "source_date": "2026-04-16",
    "scan_date": "2026-04-17",
    "raw_data": {
      "keyword": "definitive agreement",
      "filing_type": "8-K",
      "cik": "0001847345",
      "adsh": "0001493152-26-016979",
      "file_description": "EX-99.1",
      "company_raw": "Aspire Biopharma Holdings, Inc.  (ASBP, ASBPW)  (CIK 0001847345)"
    }
  },
  {
    "ticker": "FRT",
    "isin": null,
    "company_name": "FEDERAL REALTY INVESTMENT TRUST  (FRT, FRT-PC)",
    "market_cap_mm": null,
    "signal_type": "mna_keyword",
    "signal_category": "edgar",
    "strength_estimate": 5,
    "source_url": "https://www.sec.gov/Archives/edgar/data/34903/000119312526156973",
    "source_date": "2026-04-15",
    "scan_date": "2026-04-17",
    "raw_data": {
      "keyword": "definitive agreement",
      "filing_type": "8-K",
      "cik": "0000034903",
      "adsh": "0001193125-26-156973",
      "file_description": "8-K",
      "company_raw": "FEDERAL REALTY INVESTMENT TRUST  (FRT, FRT-PC)  (CIK 0000034903)"
    }
  },
  {
    "ticker": "EBS",
    "isin": null,
    "company_name": "Emergent BioSolutions Inc.  (EBS)",
    "market_cap_mm": null,
    "signal_type": "mna_keyword",
    "signal_category": "edgar",
    "strength_estimate": 5,
    "source_url": "https://www.sec.gov/Archives/edgar/data/1367644/000136764426000038",
    "source_date": "2026-04-17",
    "scan_date": "2026-04-17",
    "raw_data": {
      "keyword": "definitive agreement",
      "filing_type": "8-K",
      "cik": "0001367644",
      "adsh": "0001367644-26-000038",
      "file_description": "8-K",
      "company_raw": "Emergent BioSolutions Inc.  (EBS)  (CIK 0001367644)"
    }
  },
  {
    "ticker": "MGTX",
    "isin": null,
    "company_name": "MeiraGTx Holdings plc  (MGTX)",
    "market_cap_mm": null,
    "signal_type": "mna_keyword",
    "signal_category": "edgar",
    "strength_estimate": 5,
    "source_url": "https://www.sec.gov/Archives/edgar/data/1735438/000110465926044028",
    "source_date": "2026-04-16",
    "scan_date": "2026-04-17",
    "raw_data": {
      "keyword": "definitive agreement",
      "filing_type": "8-K",
      "cik": "0001735438",
      "adsh": "0001104659-26-044028",
      "file_description": "8-K",
      "company_raw": "MeiraGTx Holdings plc  (MGTX)  (CIK 0001735438)"
    }
  },
  {
    "ticker": "EVFM",
    "isin": null,
    "company_name": "Evofem Biosciences, Inc.  (EVFM)",
    "market_cap_mm": null,
    "signal_type": "mna_keyword",
    "signal_category": "edgar",
    "strength_estimate": 5,
    "source_url": "https://www.sec.gov/Archives/edgar/data/1618835/000149315226017082",
    "source_date": "2026-04-16",
    "scan_date": "2026-04-17",
    "raw_data": {
      "keyword": "definitive agreement",
      "filing_type": "8-K",
      "cik": "0001618835",
      "adsh": "0001493152-26-017082",
      "file_description": "8-K",
      "company_raw": "Evofem Biosciences, Inc.  (EVFM)  (CIK 0001618835)"
    }
  },
  {
    "ticker": "",
    "isin": null,
    "company_name": "HYUNDAI ABS FUNDING LLC",
    "market_cap_mm": null,
    "signal_type": "mna_keyword",
    "signal_category": "edgar",
    "strength_estimate": 5,
    "source_url": "https://www.sec.gov/Archives/edgar/data/1260125/000110465926043780",
    "source_date": "2026-04-15",
    "scan_date": "2026-04-17",
    "raw_data": {
      "keyword": "definitive agreement",
      "filing_type": "8-K",
      "cik": "0001260125",
      "adsh": "0001104659-26-043780",
      "file_description": "FORM 8-K",
      "company_raw": "HYUNDAI ABS FUNDING LLC  (CIK 0001260125)"
    }
  },
  {
    "ticker": "LYRA",
    "isin": null,
    "company_name": "Lyra Therapeutics, Inc.  (LYRA)",
    "market_cap_mm": null,
    "signal_type": "mna_keyword",
    "signal_category": "edgar",
    "strength_estimate": 5,
    "source_url": "https://www.sec.gov/Archives/edgar/data/1327273/000119312526160421",
    "source_date": "2026-04-17",
    "scan_date": "2026-04-17",
    "raw_data": {
      "keyword": "definitive agreement",
      "filing_type": "8-K",
      "cik": "0001327273",
      "adsh": "0001193125-26-160421",
      "file_description": "8-K",
      "company_raw": "Lyra Therapeutics, Inc.  (LYRA)  (CIK 0001327273)"
    }
  },
  {
    "ticker": "VS",
    "isin": null,
    "company_name": "Versus Systems Inc.  (VS)",
    "market_cap_mm": null,
    "signal_type": "mna_keyword",
    "signal_category": "edgar",
    "strength_estimate": 5,
    "source_url": "https://www.sec.gov/Archives/edgar/data/1701963/000121390026044306",
    "source_date": "2026-04-16",
    "scan_date": "2026-04-17",
    "raw_data": {
      "keyword": "definitive agreement",
      "filing_type": "8-K",
      "cik": "0001701963",
      "adsh": "0001213900-26-044306",
      "file_description": "CURRENT REPORT",
      "company_raw": "Versus Systems Inc.  (VS)  (CIK 0001701963)"
    }
  },
  {
    "ticker": "ETHB",
    "isin": null,
    "company_name": "iShares Staked Ethereum Trust ETF  (ETHB)",
    "market_cap_mm": null,
    "signal_type": "mna_keyword",
    "signal_category": "edgar",
    "strength_estimate": 5,
    "source_url": "https://www.sec.gov/Archives/edgar/data/2099103/000143774926012415",
    "source_date": "2026-04-15",
    "scan_date": "2026-04-17",
    "raw_data": {
      "keyword": "definitive agreement",
      "filing_type": "8-K",
      "cik": "0002099103",
      "adsh": "0001437749-26-012415",
      "file_description": "FORM 8-K",
      "company_raw": "iShares Staked Ethereum Trust ETF  (ETHB)  (CIK 0002099103)"
    }
  },
  {
    "ticker": "ETON",
    "isin": null,
    "company_name": "Eton Pharmaceuticals, Inc.  (ETON)",
    "market_cap_mm": null,
    "signal_type": "mna_keyword",
    "signal_category": "edgar",
    "strength_estimate": 5,
    "source_url": "https://www.sec.gov/Archives/edgar/data/1710340/000143774926012381",
    "source_date": "2026-04-15",
    "scan_date": "2026-04-17",
    "raw_data": {
      "keyword": "definitive agreement",
      "filing_type": "8-K",
      "cik": "0001710340",
      "adsh": "0001437749-26-012381",
      "file_description": "FORM 8-K",
      "company_raw": "Eton Pharmaceuticals, Inc.  (ETON)  (CIK 0001710340)"
    }
  },
  {
    "ticker": "CRC",
    "isin": null,
    "company_name": "California Resources Corp  (CRC)",
    "market_cap_mm": null,
    "signal_type": "mna_keyword",
    "signal_category": "edgar",
    "strength_estimate": 5,
    "source_url": "https://www.sec.gov/Archives/edgar/data/1609253/000160925326000086",
    "source_date": "2026-04-17",
    "scan_date": "2026-04-17",
    "raw_data": {
      "keyword": "definitive agreement",
      "filing_type": "8-K",
      "cik": "0001609253",
      "adsh": "0001609253-26-000086",
      "file_description": "8-K",
      "company_raw": "California Resources Corp  (CRC)  (CIK 0001609253)"
    }
  },
  {
    "ticker": "CBDW",
    "isin": null,
    "company_name": "1606 CORP.  (CBDW)",
    "market_cap_mm": null,
    "signal_type": "mna_keyword",
    "signal_category": "edgar",
    "strength_estimate": 5,
    "source_url": "https://www.sec.gov/Archives/edgar/data/1877461/000147793226002325",
    "source_date": "2026-04-16",
    "scan_date": "2026-04-17",
    "raw_data": {
      "keyword": "definitive agreement",
      "filing_type": "8-K",
      "cik": "0001877461",
      "adsh": "0001477932-26-002325",
      "file_description": "FORM 8-K",
      "company_raw": "1606 CORP.  (CBDW)  (CIK 0001877461)"
    }
  },
  {
    "ticker": "OPRT",
    "isin": null,
    "company_name": "Oportun Financial Corp  (OPRT)",
    "market_cap_mm": null,
    "signal_type": "mna_keyword",
    "signal_category": "edgar",
    "strength_estimate": 5,
    "source_url": "https://www.sec.gov/Archives/edgar/data/1538716/000119312526159696",
    "source_date": "2026-04-17",
    "scan_date": "2026-04-17",
    "raw_data": {
      "keyword": "definitive agreement",
      "filing_type": "8-K",
      "cik": "0001538716",
      "adsh": "0001193125-26-159696",
      "file_description": "EX-10.3",
      "company_raw": "Oportun Financial Corp  (OPRT)  (CIK 0001538716)"
    }
  },
  {
    "ticker": "NGVT",
    "isin": null,
    "company_name": "Ingevity Corp  (NGVT)",
    "market_cap_mm": null,
    "signal_type": "mna_keyword",
    "signal_category": "edgar",
    "strength_estimate": 5,
    "source_url": "https://www.sec.gov/Archives/edgar/data/1653477/000165347726000021",
    "source_date": "2026-04-15",
    "scan_date": "2026-04-17",
    "raw_data": {
      "keyword": "definitive agreement",
      "filing_type": "8-K",
      "cik": "0001653477",
      "adsh": "0001653477-26-000021",
      "file_description": "EX-99.1",
      "company_raw": "Ingevity Corp  (NGVT)  (CIK 0001653477)"
    }
  },
  {
    "ticker": "MCHX",
    "isin": null,
    "company_name": "MARCHEX INC  (MCHX)",
    "market_cap_mm": null,
    "signal_type": "mna_keyword",
    "signal_category": "edgar",
    "strength_estimate": 5,
    "source_url": "https://www.sec.gov/Archives/edgar/data/1224133/000119312526157030",
    "source_date": "2026-04-15",
    "scan_date": "2026-04-17",
    "raw_data": {
      "keyword": "definitive agreement",
      "filing_type": "8-K",
      "cik": "0001224133",
      "adsh": "0001193125-26-157030",
      "file_description": "8-K",
      "company_raw": "MARCHEX INC  (MCHX)  (CIK 0001224133)"
    }
  },
  {
    "ticker": "XWIN",
    "isin": null,
    "company_name": "XMax Inc.  (XWIN)",
    "market_cap_mm": null,
    "signal_type": "mna_keyword",
    "signal_category": "edgar",
    "strength_estimate": 5,
    "source_url": "https://www.sec.gov/Archives/edgar/data/1473334/000149315226016970",
    "source_date": "2026-04-16",
    "scan_date": "2026-04-17",
    "raw_data": {
      "keyword": "definitive agreement",
      "filing_type": "8-K",
      "cik": "0001473334",
      "adsh": "0001493152-26-016970",
      "file_description": "8-K",
      "company_raw": "XMax Inc.  (XWIN)  (CIK 0001473334)"
    }
  },
  {
    "ticker": "KVAC",
    "isin": null,
    "company_name": "Keen Vision Acquisition Corp.  (KVAC, KVACU, KVACW)",
    "market_cap_mm": null,
    "signal_type": "mna_keyword",
    "signal_category": "edgar",
    "strength_estimate": 5,
    "source_url": "https://www.sec.gov/Archives/edgar/data/1889983/000121390026043759",
    "source_date": "2026-04-15",
    "scan_date": "2026-04-17",
    "raw_data": {
      "keyword": "definitive agreement",
      "filing_type": "8-K",
      "cik": "0001889983",
      "adsh": "0001213900-26-043759",
      "file_description": "CURRENT REPORT",
      "company_raw": "Keen Vision Acquisition Corp.  (KVAC, KVACU, KVACW)  (CIK 0001889983)"
    }
  }
]