[
  {
    "ticker": "MSPR",
    "isin": null,
    "company_name": "MSP Recovery, Inc.  (MSPR, MSPRW, MSPRZ)",
    "market_cap_mm": null,
    "signal_type": "distress_keyword",
    "signal_category": "edgar",
    "strength_estimate": 2,
    "source_url": "https://www.sec.gov/Archives/edgar/data/1802450/000180245026000019",
    "source_date": "2026-04-20",
    "scan_date": "2026-04-21",
    "raw_data": {
      "keyword": "debtor-in-possession",
      "filing_type": "8-K",
      "cik": "0001802450",
      "adsh": "0001802450-26-000019",
      "file_description": "EX-10.1",
      "company_raw": "MSP Recovery, Inc.  (MSPR, MSPRW, MSPRZ)  (CIK 0001802450)"
    }
  },
  {
    "ticker": "BIRD",
    "isin": null,
    "company_name": "Allbirds, Inc.  (BIRD)",
    "market_cap_mm": null,
    "signal_type": "distress_keyword",
    "signal_category": "edgar",
    "strength_estimate": 2,
    "source_url": "https://www.sec.gov/Archives/edgar/data/1653909/000119312526164338",
    "source_date": "2026-04-20",
    "scan_date": "2026-04-21",
    "raw_data": {
      "keyword": "debtor-in-possession",
      "filing_type": "8-K",
      "cik": "0001653909",
      "adsh": "0001193125-26-164338",
      "file_description": "EX-10.6",
      "company_raw": "Allbirds, Inc.  (BIRD)  (CIK 0001653909)"
    }
  },
  {
    "ticker": "",
    "isin": null,
    "company_name": "CHARLES & COLVARD LTD",
    "market_cap_mm": null,
    "signal_type": "distress_keyword",
    "signal_category": "edgar",
    "strength_estimate": 2,
    "source_url": "https://www.sec.gov/Archives/edgar/data/1015155/000110465926045530",
    "source_date": "2026-04-20",
    "scan_date": "2026-04-21",
    "raw_data": {
      "keyword": "debtor-in-possession",
      "filing_type": "8-K",
      "cik": "0001015155",
      "adsh": "0001104659-26-045530",
      "file_description": "EXHIBIT 10.1",
      "company_raw": "CHARLES & COLVARD LTD  (CIK 0001015155)"
    }
  },
  {
    "ticker": "FMC",
    "isin": null,
    "company_name": "FMC CORP  (FMC)",
    "market_cap_mm": null,
    "signal_type": "distress_keyword",
    "signal_category": "edgar",
    "strength_estimate": 2,
    "source_url": "https://www.sec.gov/Archives/edgar/data/37785/000119312526163937",
    "source_date": "2026-04-20",
    "scan_date": "2026-04-21",
    "raw_data": {
      "keyword": "debtor-in-possession",
      "filing_type": "8-K",
      "cik": "0000037785",
      "adsh": "0001193125-26-163937",
      "file_description": "EX-10.1",
      "company_raw": "FMC CORP  (FMC)  (CIK 0000037785)"
    }
  },
  {
    "ticker": "",
    "isin": null,
    "company_name": "ExchangeRight Income Fund",
    "market_cap_mm": null,
    "signal_type": "distress_keyword",
    "signal_category": "edgar",
    "strength_estimate": 2,
    "source_url": "https://www.sec.gov/Archives/edgar/data/1771514/000119312526163165",
    "source_date": "2026-04-20",
    "scan_date": "2026-04-21",
    "raw_data": {
      "keyword": "debtor-in-possession",
      "filing_type": "8-K",
      "cik": "0001771514",
      "adsh": "0001193125-26-163165",
      "file_description": "EX-10.1",
      "company_raw": "ExchangeRight Income Fund  (CIK 0001771514)"
    }
  },
  {
    "ticker": "SILA",
    "isin": null,
    "company_name": "Sila Realty Trust, Inc.  (SILA)",
    "market_cap_mm": null,
    "signal_type": "mna_keyword",
    "signal_category": "edgar",
    "strength_estimate": 5,
    "source_url": "https://www.sec.gov/Archives/edgar/data/1567925/000114036126015496",
    "source_date": "2026-04-20",
    "scan_date": "2026-04-21",
    "raw_data": {
      "keyword": "merger agreement",
      "filing_type": "8-K",
      "cik": "0001567925",
      "adsh": "0001140361-26-015496",
      "file_description": "8-K",
      "company_raw": "Sila Realty Trust, Inc.  (SILA)  (CIK 0001567925)"
    }
  },
  {
    "ticker": "USAR",
    "isin": null,
    "company_name": "USA Rare Earth, Inc.  (USAR)",
    "market_cap_mm": null,
    "signal_type": "mna_keyword",
    "signal_category": "edgar",
    "strength_estimate": 5,
    "source_url": "https://www.sec.gov/Archives/edgar/data/1970622/000121390026045339",
    "source_date": "2026-04-20",
    "scan_date": "2026-04-21",
    "raw_data": {
      "keyword": "merger agreement",
      "filing_type": "8-K",
      "cik": "0001970622",
      "adsh": "0001213900-26-045339",
      "file_description": "CURRENT REPORT",
      "company_raw": "USA Rare Earth, Inc.  (USAR)  (CIK 0001970622)"
    }
  },
  {
    "ticker": "BLD",
    "isin": null,
    "company_name": "TopBuild Corp  (BLD)",
    "market_cap_mm": null,
    "signal_type": "mna_keyword",
    "signal_category": "edgar",
    "strength_estimate": 5,
    "source_url": "https://www.sec.gov/Archives/edgar/data/1633931/000110465926045245",
    "source_date": "2026-04-20",
    "scan_date": "2026-04-21",
    "raw_data": {
      "keyword": "merger agreement",
      "filing_type": "8-K",
      "cik": "0001633931",
      "adsh": "0001104659-26-045245",
      "file_description": "8-K",
      "company_raw": "TopBuild Corp  (BLD)  (CIK 0001633931)"
    }
  },
  {
    "ticker": "MCW",
    "isin": null,
    "company_name": "Mister Car Wash, Inc.  (MCW)",
    "market_cap_mm": null,
    "signal_type": "mna_keyword",
    "signal_category": "edgar",
    "strength_estimate": 2,
    "source_url": "https://www.sec.gov/Archives/edgar/data/1853513/000119312526162903",
    "source_date": "2026-04-20",
    "scan_date": "2026-04-21",
    "raw_data": {
      "keyword": "merger agreement",
      "filing_type": "SC 13E3/A",
      "cik": "0001853513",
      "adsh": "0001193125-26-162903",
      "file_description": "SC 13E3/A",
      "company_raw": "Mister Car Wash, Inc.  (MCW)  (CIK 0001853513)"
    }
  },
  {
    "ticker": "ATII",
    "isin": null,
    "company_name": "Archimedes Tech SPAC Partners II Co.  (ATII, ATIIU, ATIIW)",
    "market_cap_mm": null,
    "signal_type": "mna_keyword",
    "signal_category": "edgar",
    "strength_estimate": 5,
    "source_url": "https://www.sec.gov/Archives/edgar/data/2028516/000143774926012856",
    "source_date": "2026-04-20",
    "scan_date": "2026-04-21",
    "raw_data": {
      "keyword": "merger agreement",
      "filing_type": "8-K",
      "cik": "0002028516",
      "adsh": "0001437749-26-012856",
      "file_description": "FORM 8-K",
      "company_raw": "Archimedes Tech SPAC Partners II Co.  (ATII, ATIIU, ATIIW)  (CIK 0002028516)"
    }
  },
  {
    "ticker": "SLNO",
    "isin": null,
    "company_name": "SOLENO THERAPEUTICS INC  (SLNO)",
    "market_cap_mm": null,
    "signal_type": "mna_keyword",
    "signal_category": "edgar",
    "strength_estimate": 2,
    "source_url": "https://www.sec.gov/Archives/edgar/data/1484565/000119312526162715",
    "source_date": "2026-04-20",
    "scan_date": "2026-04-21",
    "raw_data": {
      "keyword": "merger agreement",
      "filing_type": "SC TO-T",
      "cik": "0001484565",
      "adsh": "0001193125-26-162715",
      "file_description": "EX-99.(A)(1)(A)",
      "company_raw": "SOLENO THERAPEUTICS INC  (SLNO)  (CIK 0001484565)"
    }
  },
  {
    "ticker": "QXO",
    "isin": null,
    "company_name": "QXO, Inc.  (QXO, QXO-PB)",
    "market_cap_mm": null,
    "signal_type": "mna_keyword",
    "signal_category": "edgar",
    "strength_estimate": 5,
    "source_url": "https://www.sec.gov/Archives/edgar/data/1236275/000110465926045111",
    "source_date": "2026-04-20",
    "scan_date": "2026-04-21",
    "raw_data": {
      "keyword": "merger agreement",
      "filing_type": "8-K",
      "cik": "0001236275",
      "adsh": "0001104659-26-045111",
      "file_description": "FORM 8-K",
      "company_raw": "QXO, Inc.  (QXO, QXO-PB)  (CIK 0001236275)"
    }
  },
  {
    "ticker": "CMCAF",
    "isin": null,
    "company_name": "Piermont Valley Acquisition Corp  (CMCAF, CMCUF, CMCWF)",
    "market_cap_mm": null,
    "signal_type": "mna_keyword",
    "signal_category": "edgar",
    "strength_estimate": 5,
    "source_url": "https://www.sec.gov/Archives/edgar/data/1865248/000147793226002395",
    "source_date": "2026-04-20",
    "scan_date": "2026-04-21",
    "raw_data": {
      "keyword": "merger agreement",
      "filing_type": "8-K",
      "cik": "0001865248",
      "adsh": "0001477932-26-002395",
      "file_description": "FORM 8-K",
      "company_raw": "Piermont Valley Acquisition Corp  (CMCAF, CMCUF, CMCWF)  (CIK 0001865248)"
    }
  },
  {
    "ticker": "LEEEF",
    "isin": null,
    "company_name": "Leef Brands Inc.  (LEEEF)",
    "market_cap_mm": null,
    "signal_type": "mna_keyword",
    "signal_category": "edgar",
    "strength_estimate": 5,
    "source_url": "https://www.sec.gov/Archives/edgar/data/1711141/000149315226018032",
    "source_date": "2026-04-20",
    "scan_date": "2026-04-21",
    "raw_data": {
      "keyword": "merger agreement",
      "filing_type": "8-K",
      "cik": "0001711141",
      "adsh": "0001493152-26-018032",
      "file_description": "8-K",
      "company_raw": "Leef Brands Inc.  (LEEEF)  (CIK 0001711141)"
    }
  },
  {
    "ticker": "SLNO",
    "isin": null,
    "company_name": "SOLENO THERAPEUTICS INC  (SLNO)",
    "market_cap_mm": null,
    "signal_type": "mna_keyword",
    "signal_category": "edgar",
    "strength_estimate": 4,
    "source_url": "https://www.sec.gov/Archives/edgar/data/1484565/000119312526162715",
    "source_date": "2026-04-20",
    "scan_date": "2026-04-21",
    "raw_data": {
      "keyword": "tender offer",
      "filing_type": "SC TO-T",
      "cik": "0001484565",
      "adsh": "0001193125-26-162715",
      "file_description": "SC TO-T",
      "company_raw": "SOLENO THERAPEUTICS INC  (SLNO)  (CIK 0001484565)"
    }
  },
  {
    "ticker": "CEG",
    "isin": null,
    "company_name": "Constellation Energy Corp  (CEG)",
    "market_cap_mm": null,
    "signal_type": "mna_keyword",
    "signal_category": "edgar",
    "strength_estimate": 2,
    "source_url": "https://www.sec.gov/Archives/edgar/data/1868275/000110465926045036",
    "source_date": "2026-04-20",
    "scan_date": "2026-04-21",
    "raw_data": {
      "keyword": "tender offer",
      "filing_type": "8-K/A",
      "cik": "0001868275",
      "adsh": "0001104659-26-045036",
      "file_description": "FORM 8-K/A",
      "company_raw": "Constellation Energy Corp  (CEG)  (CIK 0001868275)"
    }
  },
  {
    "ticker": "AXTI",
    "isin": null,
    "company_name": "AXT INC  (AXTI)",
    "market_cap_mm": null,
    "signal_type": "mna_keyword",
    "signal_category": "edgar",
    "strength_estimate": 2,
    "source_url": "https://www.sec.gov/Archives/edgar/data/1051627/000121390026045867",
    "source_date": "2026-04-21",
    "scan_date": "2026-04-21",
    "raw_data": {
      "keyword": "tender offer",
      "filing_type": "8-K",
      "cik": "0001051627",
      "adsh": "0001213900-26-045867",
      "file_description": "FORM OF LOCK UP AGREEMENT",
      "company_raw": "AXT INC  (AXTI)  (CIK 0001051627)"
    }
  },
  {
    "ticker": "",
    "isin": null,
    "company_name": "JATT II Acquisition Corp.",
    "market_cap_mm": null,
    "signal_type": "mna_keyword",
    "signal_category": "edgar",
    "strength_estimate": 2,
    "source_url": "https://www.sec.gov/Archives/edgar/data/2112446/000121390026045819",
    "source_date": "2026-04-21",
    "scan_date": "2026-04-21",
    "raw_data": {
      "keyword": "tender offer",
      "filing_type": "8-K",
      "cik": "0002112446",
      "adsh": "0001213900-26-045819",
      "file_description": "LETTER AGREEMENT, DATED APRIL 16, 2026, AMONG THE COMPANY, JATT VENTURES II L.P. AND EACH OF THE OFFICERS AND DIRECTORS OF THE COMPANY",
      "company_raw": "JATT II Acquisition Corp.  (CIK 0002112446)"
    }
  },
  {
    "ticker": "CSCIF",
    "isin": null,
    "company_name": "COSCIENS Biopharma Inc.  (CSCIF)",
    "market_cap_mm": null,
    "signal_type": "mna_keyword",
    "signal_category": "edgar",
    "strength_estimate": 3,
    "source_url": "https://www.sec.gov/Archives/edgar/data/1113423/000149315226018001",
    "source_date": "2026-04-20",
    "scan_date": "2026-04-21",
    "raw_data": {
      "keyword": "fairness opinion",
      "filing_type": "SC 13E3",
      "cik": "0001113423",
      "adsh": "0001493152-26-018001",
      "file_description": "EX-99.(A)(C)",
      "company_raw": "COSCIENS Biopharma Inc.  (CSCIF)  (CIK 0001113423)"
    }
  },
  {
    "ticker": "PEBO",
    "isin": null,
    "company_name": "PEOPLES BANCORP INC  (PEBO)",
    "market_cap_mm": null,
    "signal_type": "mna_keyword",
    "signal_category": "edgar",
    "strength_estimate": 3,
    "source_url": "https://www.sec.gov/Archives/edgar/data/318300/000031830026000142",
    "source_date": "2026-04-21",
    "scan_date": "2026-04-21",
    "raw_data": {
      "keyword": "fairness opinion",
      "filing_type": "8-K",
      "cik": "0000318300",
      "adsh": "0000318300-26-000142",
      "file_description": "EX-99.4",
      "company_raw": "PEOPLES BANCORP INC  (PEBO)  (CIK 0000318300)"
    }
  },
  {
    "ticker": "MCW",
    "isin": null,
    "company_name": "Mister Car Wash, Inc.  (MCW)",
    "market_cap_mm": null,
    "signal_type": "mna_keyword",
    "signal_category": "edgar",
    "strength_estimate": 3,
    "source_url": "https://www.sec.gov/Archives/edgar/data/1853513/000119312526162903",
    "source_date": "2026-04-20",
    "scan_date": "2026-04-21",
    "raw_data": {
      "keyword": "fairness opinion",
      "filing_type": "SC 13E3/A",
      "cik": "0001853513",
      "adsh": "0001193125-26-162903",
      "file_description": "SC 13E3/A",
      "company_raw": "Mister Car Wash, Inc.  (MCW)  (CIK 0001853513)"
    }
  }
]