{"_fetched_at": "2026-04-17T18:34:18.349190+00:00", "status": 200, "data": {"description": "BARRATT REDROW PLC ORD 10P", "name": "ORD 10P", "tidm": "BTRW", "topic": "TIT.BTRW.LD", "isin": "GB0000811801", "sedol": "0081180", "category": "EQUITY", "mifir": "SHRS", "country": "GB", "csm": "MAINMARKET.SET1.LSEUK", "market": "MAINMARKET", "segment": "SET1", "lipperId": "20000085", "marketvolume": null, "tradingdate": null, "fundsType": "NONE", "mifid": null, "currency": "GBX", "suspend": null, "bid": 279, "offer": 279.1, "volume": 9777746, "turnover": 1705138593.6, "fiftyTwoWeeksMin": 249.3, "fiftyTwoWeeksMax": 486.499, "high": 282.1, "low": 264, "midPrice": 282.5, "underlying": null, "issuercode": "BAUNQ", "issuername": "BARRATT REDROW PLC", "shortname": "BARRATT REDROW", "instrumenttype": "STOCK", "marketsize": 5000, "tradingstatuscode": "N c", "tradingstatus": "N", "periodcode": "c", "openingprice": 269, "specialconditions": "XD", "ismidprice": false, "lastvolume": null, "lastturnover": null, "fourwaykey": "GB0000811801GBGBXSET1", "marketcapitalization": 3796301680, "listingadmissiondate": "2007-06-18", "sectorcode": "402020", "subsectorcode": "40202010", "datelastnews": "2026-04-17T13:08:31.000", "presentnews": true, "istodaynews": true, "idnews": 17552892, "sectioncodenews": "BRK", "subjectnews": "Holding(s) in Company", "previoussectioncodenews": null, "annualreportweeklyurl": null, "netchangesign": "+1", "datepreviousnews": null, "previousreferenceprice": 268.3, "netchange": 10.8, "percentualchange": 4.025344763324637, "cwtype": null, "strikeprice": null, "strikepricecurrency": null, "maturitydate": null, "subSearchTags": null, "islse": true, "lastprice": 279.1, "lastpricedate": "2026-04-17T15:48:42.000", "lastclose": 279.1, "lastclosedate": "2026-04-17T15:35:14.000"}}