{"_fetched_at": "2026-04-16T06:51:00.069941+00:00", "status": 200, "data": {"description": "AUDIOBOOM GROUP PLC ORD SHS NPV", "name": "ORD SHS NPV", "tidm": "BOOM", "topic": "TIT.BOOM.LD", "isin": "JE00BJYJFG60", "sedol": "BJYJFG6", "category": "EQUITY", "mifir": "SHRS", "country": "JE", "csm": "AIM.ASQ1.LSEUK", "market": "AIM", "segment": "ASQ1", "lipperId": null, "marketvolume": null, "tradingdate": null, "fundsType": "NONE", "mifid": null, "currency": "GBX", "suspend": null, "bid": 630.0, "offer": 660.0, "volume": null, "turnover": null, "fiftyTwoWeeksMin": 270.0, "fiftyTwoWeeksMax": 810.0, "high": null, "low": null, "midPrice": 645, "underlying": null, "issuercode": "AUBOOM", "issuername": "AUDIOBOOM GROUP PLC", "shortname": "AUDIOBOOM GRP.", "instrumenttype": "STOCK", "marketsize": 1500, "tradingstatuscode": "N m", "tradingstatus": "N", "periodcode": "m", "openingprice": null, "specialconditions": null, "ismidprice": true, "lastvolume": null, "lastturnover": null, "fourwaykey": "JE00BJYJFG60JEGBXASQ1", "marketcapitalization": 113303327, "listingadmissiondate": "2019-06-21", "sectorcode": "101010", "subsectorcode": "10101020", "datelastnews": "2026-04-16T06:00:10.000", "presentnews": true, "istodaynews": true, "idnews": 17549237, "sectioncodenews": "BRK", "subjectnews": "Q1 Trading Update", "previoussectioncodenews": null, "annualreportweeklyurl": null, "netchangesign": "+1", "datepreviousnews": null, "previousreferenceprice": 630.0, "netchange": 15, "percentualchange": 2.381, "cwtype": null, "strikeprice": null, "strikepricecurrency": null, "maturitydate": null, "subSearchTags": null, "islse": true, "lastprice": 645, "lastpricedate": null, "lastclose": 630.0, "lastclosedate": "2026-04-15T00:00:00.000"}}