{"_fetched_at": "2026-04-15T21:07:54.929301+00:00", "status": 200, "data": {"description": "CIRATA PLC ORD 10P", "name": "ORD 10P", "tidm": "CRTA", "topic": "TIT.CRTA.LD", "isin": "JE00B6Y3DV84", "sedol": "B6Y3DV8", "category": "EQUITY", "mifir": "SHRS", "country": "JE", "csm": "AIM.AMSM.LSEUK", "market": "AIM", "segment": "AMSM", "lipperId": "29915813", "marketvolume": null, "tradingdate": null, "fundsType": "NONE", "mifid": null, "currency": "GBX", "suspend": null, "bid": 15.5, "offer": 16, "volume": 1280, "turnover": 3296, "fiftyTwoWeeksMin": 12.5, "fiftyTwoWeeksMax": 39.1, "high": 16, "low": 16, "midPrice": 15.75, "underlying": null, "issuercode": "WAWAND", "issuername": "CIRATA PLC", "shortname": "CIRATA", "instrumenttype": "STOCK", "marketsize": 15000, "tradingstatuscode": "N c", "tradingstatus": "N", "periodcode": "c", "openingprice": 16, "specialconditions": null, "ismidprice": false, "lastvolume": null, "lastturnover": null, "fourwaykey": "JE00B6Y3DV84JEGBXAMSM", "marketcapitalization": 20863764, "listingadmissiondate": "2012-06-01", "sectorcode": "101010", "subsectorcode": "10101015", "datelastnews": null, "presentnews": true, "istodaynews": false, "idnews": 17544741, "sectioncodenews": null, "subjectnews": "Trading Statement", "previoussectioncodenews": "BRK", "annualreportweeklyurl": null, "netchangesign": "-1", "datepreviousnews": "2026-04-14T06:00:04.000", "previousreferenceprice": 16.5, "netchange": -0.5, "percentualchange": -3.03030303030303, "cwtype": null, "strikeprice": null, "strikepricecurrency": null, "maturitydate": null, "subSearchTags": null, "islse": true, "lastprice": 16, "lastpricedate": "2026-04-15T15:35:20.000", "lastclose": 16, "lastclosedate": "2026-04-15T15:35:20.000"}}