[
  {
    "regulator": "AMF",
    "holder_name": "AHL Partners LLP",
    "target_company": "REMY COINTREAU",
    "isin": "FR0000130395",
    "position_pct": 1.09,
    "position_date": "2026-03-24",
    "previous_position_pct": 1.09,
    "change_pct": 0.0,
    "disclosure_date": "2026-03-25"
  },
  {
    "regulator": "AMF",
    "holder_name": "AKO CAPITAL LLP",
    "target_company": "ALSTOM",
    "isin": "FR0010220475",
    "position_pct": 1.1,
    "position_date": "2026-04-08",
    "previous_position_pct": 1.1,
    "change_pct": 0.0,
    "disclosure_date": "2026-04-09"
  },
  {
    "regulator": "AMF",
    "holder_name": "AKO CAPITAL LLP",
    "target_company": "BIOMERIEUX",
    "isin": "FR0013280286",
    "position_pct": 0.58,
    "position_date": "2026-03-19",
    "previous_position_pct": 0.58,
    "change_pct": 0.0,
    "disclosure_date": "2026-03-20"
  },
  {
    "regulator": "AMF",
    "holder_name": "AKO CAPITAL LLP",
    "target_company": "PERNOD RICARD",
    "isin": "FR0000120693",
    "position_pct": 0.61,
    "position_date": "2026-04-08",
    "previous_position_pct": 0.61,
    "change_pct": 0.0,
    "disclosure_date": "2026-04-09"
  },
  {
    "regulator": "AMF",
    "holder_name": "AKO CAPITAL LLP",
    "target_company": "SOPRA STERIA GROUP",
    "isin": "FR0000050809",
    "position_pct": 0.81,
    "position_date": "2026-03-19",
    "previous_position_pct": 0.81,
    "change_pct": 0.0,
    "disclosure_date": "2026-03-20"
  },
  {
    "regulator": "AMF",
    "holder_name": "ANCHOR BOLT CAPITAL, LP",
    "target_company": "FORVIA",
    "isin": "FR0000121147",
    "position_pct": 0.56,
    "position_date": "2019-01-21",
    "previous_position_pct": 0.56,
    "change_pct": 0.0,
    "disclosure_date": "2019-01-22"
  },
  {
    "regulator": "AMF",
    "holder_name": "AQR CAPITAL MANAGEMENT, LLC",
    "target_company": "ACCOR",
    "isin": "FR0000120404",
    "position_pct": 0.81,
    "position_date": "2025-12-18",
    "previous_position_pct": 0.81,
    "change_pct": 0.0,
    "disclosure_date": "2025-12-19"
  },
  {
    "regulator": "AMF",
    "holder_name": "AQR CAPITAL MANAGEMENT, LLC",
    "target_company": "ALSTOM",
    "isin": "FR0010220475",
    "position_pct": 0.69,
    "position_date": "2026-01-09",
    "previous_position_pct": 0.69,
    "change_pct": 0.0,
    "disclosure_date": "2026-01-12"
  },
  {
    "regulator": "AMF",
    "holder_name": "AQR CAPITAL MANAGEMENT, LLC",
    "target_company": "ARKEMA",
    "isin": "FR0010313833",
    "position_pct": 0.59,
    "position_date": "2026-03-18",
    "previous_position_pct": 0.59,
    "change_pct": 0.0,
    "disclosure_date": "2026-03-19"
  },
  {
    "regulator": "AMF",
    "holder_name": "AQR CAPITAL MANAGEMENT, LLC",
    "target_company": "BIOMERIEUX",
    "isin": "FR0013280286",
    "position_pct": 0.6,
    "position_date": "2025-11-17",
    "previous_position_pct": 0.6,
    "change_pct": 0.0,
    "disclosure_date": "2025-11-18"
  },
  {
    "regulator": "AMF",
    "holder_name": "AQR CAPITAL MANAGEMENT, LLC",
    "target_company": "BUREAU VERITAS",
    "isin": "FR0006174348",
    "position_pct": 0.59,
    "position_date": "2025-10-13",
    "previous_position_pct": 0.59,
    "change_pct": 0.0,
    "disclosure_date": "2025-10-14"
  },
  {
    "regulator": "AMF",
    "holder_name": "AQR CAPITAL MANAGEMENT, LLC",
    "target_company": "CAPGEMINI",
    "isin": "FR0000125338",
    "position_pct": 0.69,
    "position_date": "2025-10-23",
    "previous_position_pct": 0.69,
    "change_pct": 0.0,
    "disclosure_date": "2025-10-24"
  },
  {
    "regulator": "AMF",
    "holder_name": "AQR CAPITAL MANAGEMENT, LLC",
    "target_company": "COMPAGNIE GENERALE DES ETABLISSEMENTS MICHELIN",
    "isin": "FR001400AJ45",
    "position_pct": 0.8,
    "position_date": "2026-03-19",
    "previous_position_pct": 0.8,
    "change_pct": 0.0,
    "disclosure_date": "2026-03-20"
  },
  {
    "regulator": "AMF",
    "holder_name": "AQR CAPITAL MANAGEMENT, LLC",
    "target_company": "DASSAULT SYSTEMES",
    "isin": "FR0014003TT8",
    "position_pct": 0.9,
    "position_date": "2026-04-01",
    "previous_position_pct": 0.9,
    "change_pct": 0.0,
    "disclosure_date": "2026-04-02"
  },
  {
    "regulator": "AMF",
    "holder_name": "AQR CAPITAL MANAGEMENT, LLC",
    "target_company": "EDENRED",
    "isin": "FR0010908533",
    "position_pct": 0.91,
    "position_date": "2026-04-08",
    "previous_position_pct": 0.91,
    "change_pct": 0.0,
    "disclosure_date": "2026-04-09"
  },
  {
    "regulator": "AMF",
    "holder_name": "AQR CAPITAL MANAGEMENT, LLC",
    "target_company": "FDJ UNITED",
    "isin": "FR0013451333",
    "position_pct": 0.82,
    "position_date": "2026-03-24",
    "previous_position_pct": 0.82,
    "change_pct": 0.0,
    "disclosure_date": "2026-03-25"
  },
  {
    "regulator": "AMF",
    "holder_name": "AQR CAPITAL MANAGEMENT, LLC",
    "target_company": "NEXITY",
    "isin": "FR0010112524",
    "position_pct": 0.7,
    "position_date": "2026-03-23",
    "previous_position_pct": 0.7,
    "change_pct": 0.0,
    "disclosure_date": "2026-03-24"
  },
  {
    "regulator": "AMF",
    "holder_name": "AQR CAPITAL MANAGEMENT, LLC",
    "target_company": "PERNOD RICARD",
    "isin": "FR0000120693",
    "position_pct": 1.32,
    "position_date": "2026-04-02",
    "previous_position_pct": 1.32,
    "change_pct": 0.0,
    "disclosure_date": "2026-04-03"
  },
  {
    "regulator": "AMF",
    "holder_name": "AQR CAPITAL MANAGEMENT, LLC",
    "target_company": "REMY COINTREAU",
    "isin": "FR0000130395",
    "position_pct": 2.6,
    "position_date": "2026-04-01",
    "previous_position_pct": 2.6,
    "change_pct": 0.0,
    "disclosure_date": "2026-04-02"
  },
  {
    "regulator": "AMF",
    "holder_name": "AQR CAPITAL MANAGEMENT, LLC",
    "target_company": "SCOR SE",
    "isin": "FR0010411983",
    "position_pct": 0.5,
    "position_date": "2026-04-01",
    "previous_position_pct": 0.5,
    "change_pct": 0.0,
    "disclosure_date": "2026-04-02"
  },
  {
    "regulator": "AMF",
    "holder_name": "AQR CAPITAL MANAGEMENT, LLC",
    "target_company": "SODEXO",
    "isin": "FR0000121220",
    "position_pct": 1.2,
    "position_date": "2026-04-01",
    "previous_position_pct": 1.2,
    "change_pct": 0.0,
    "disclosure_date": "2026-04-02"
  },
  {
    "regulator": "AMF",
    "holder_name": "AQR CAPITAL MANAGEMENT, LLC",
    "target_company": "SPIE SA",
    "isin": "FR0012757854",
    "position_pct": 1.12,
    "position_date": "2026-04-02",
    "previous_position_pct": 1.12,
    "change_pct": 0.0,
    "disclosure_date": "2026-04-03"
  },
  {
    "regulator": "AMF",
    "holder_name": "AQR CAPITAL MANAGEMENT, LLC",
    "target_company": "TELEPERFORMANCE",
    "isin": "FR0000051807",
    "position_pct": 0.71,
    "position_date": "2026-04-08",
    "previous_position_pct": 0.71,
    "change_pct": 0.0,
    "disclosure_date": "2026-04-09"
  },
  {
    "regulator": "AMF",
    "holder_name": "ARGONAUT CAPITAL PARTNERS LLP",
    "target_company": "UBISOFT ENTERTAINMENT",
    "isin": "FR0000054470",
    "position_pct": 1.86,
    "position_date": "2026-02-10",
    "previous_position_pct": 1.86,
    "change_pct": 0.0,
    "disclosure_date": "2026-02-27"
  },
  {
    "regulator": "AMF",
    "holder_name": "ARROWSTREET CAPITAL, LIMITED PARTNERSHIP",
    "target_company": "ABIVAX",
    "isin": "FR0012333284",
    "position_pct": 0.71,
    "position_date": "2026-03-25",
    "previous_position_pct": 0.71,
    "change_pct": 0.0,
    "disclosure_date": "2026-03-26"
  },
  {
    "regulator": "AMF",
    "holder_name": "ARROWSTREET CAPITAL, LIMITED PARTNERSHIP",
    "target_company": "ERAMET",
    "isin": "FR0000131757",
    "position_pct": 0.6,
    "position_date": "2025-01-14",
    "previous_position_pct": 0.6,
    "change_pct": 0.0,
    "disclosure_date": "2025-01-15"
  },
  {
    "regulator": "AMF",
    "holder_name": "ARROWSTREET CAPITAL, LIMITED PARTNERSHIP",
    "target_company": "INVENTIVA",
    "isin": "FR0013233012",
    "position_pct": 0.7,
    "position_date": "2026-02-09",
    "previous_position_pct": 0.7,
    "change_pct": 0.0,
    "disclosure_date": "2026-02-10"
  },
  {
    "regulator": "AMF",
    "holder_name": "ARROWSTREET CAPITAL, LIMITED PARTNERSHIP",
    "target_company": "STIF",
    "isin": "FR001400MDW2",
    "position_pct": 0.7,
    "position_date": "2026-03-26",
    "previous_position_pct": 0.7,
    "change_pct": 0.0,
    "disclosure_date": "2026-03-27"
  },
  {
    "regulator": "AMF",
    "holder_name": "Acadian Asset Management LLC",
    "target_company": "REMY COINTREAU",
    "isin": "FR0000130395",
    "position_pct": 0.71,
    "position_date": "2026-01-27",
    "previous_position_pct": 0.71,
    "change_pct": 0.0,
    "disclosure_date": "2026-01-28"
  },
  {
    "regulator": "AMF",
    "holder_name": "ActusRayPartners Limited",
    "target_company": "SOLUTIONS 30 SE",
    "isin": "FR0013379484",
    "position_pct": 0.62,
    "position_date": "2026-04-08",
    "previous_position_pct": 0.62,
    "change_pct": 0.0,
    "disclosure_date": "2026-04-09"
  },
  {
    "regulator": "AMF",
    "holder_name": "BALYASNY ASSET MANAGEMENT (UK) LLP",
    "target_company": "ARKEMA",
    "isin": "FR0010313833",
    "position_pct": 0.69,
    "position_date": "2026-04-07",
    "previous_position_pct": 0.69,
    "change_pct": 0.0,
    "disclosure_date": "2026-04-08"
  },
  {
    "regulator": "AMF",
    "holder_name": "BG MASTER FUND ICAV",
    "target_company": "SMCP",
    "isin": "FR0013214145",
    "position_pct": 2.52,
    "position_date": "2025-01-27",
    "previous_position_pct": 2.52,
    "change_pct": 0.0,
    "disclosure_date": "2025-01-28"
  },
  {
    "regulator": "AMF",
    "holder_name": "BLACKROCK ADVISORS, LLC",
    "target_company": "REXEL",
    "isin": "FR0010451203",
    "position_pct": 0.59,
    "position_date": "2026-03-05",
    "previous_position_pct": 0.59,
    "change_pct": 0.0,
    "disclosure_date": "2026-03-06"
  },
  {
    "regulator": "AMF",
    "holder_name": "BLACKROCK ADVISORS, LLC",
    "target_company": "SCOR SE",
    "isin": "FR0010411983",
    "position_pct": 0.63,
    "position_date": "2026-04-07",
    "previous_position_pct": 0.63,
    "change_pct": 0.0,
    "disclosure_date": "2026-04-08"
  },
  {
    "regulator": "AMF",
    "holder_name": "BLACKROCK FINANCIAL MANAGEMENT INC.",
    "target_company": "AEROPORTS DE PARIS",
    "isin": "FR0010340141",
    "position_pct": 0.5,
    "position_date": "2025-11-06",
    "previous_position_pct": 0.5,
    "change_pct": 0.0,
    "disclosure_date": "2025-11-07"
  },
  {
    "regulator": "AMF",
    "holder_name": "BLACKROCK FINANCIAL MANAGEMENT INC.",
    "target_company": "TELEPERFORMANCE",
    "isin": "FR0000051807",
    "position_pct": 0.61,
    "position_date": "2026-04-08",
    "previous_position_pct": 0.61,
    "change_pct": 0.0,
    "disclosure_date": "2026-04-09"
  },
  {
    "regulator": "AMF",
    "holder_name": "BLACKROCK INVESTMENT MANAGEMENT (UK) LIMITED",
    "target_company": "CARREFOUR",
    "isin": "FR0000120172",
    "position_pct": 0.7,
    "position_date": "2026-04-02",
    "previous_position_pct": 0.7,
    "change_pct": 0.0,
    "disclosure_date": "2026-04-03"
  },
  {
    "regulator": "AMF",
    "holder_name": "BLACKROCK INVESTMENT MANAGEMENT (UK) LIMITED",
    "target_company": "RENAULT",
    "isin": "FR0000131906",
    "position_pct": 0.87,
    "position_date": "2026-02-13",
    "previous_position_pct": 0.87,
    "change_pct": 0.0,
    "disclosure_date": "2026-02-16"
  },
  {
    "regulator": "AMF",
    "holder_name": "BLACKROCK INVESTMENT MANAGEMENT (UK) LIMITED",
    "target_company": "TELEVISION FRANCAISE 1",
    "isin": "FR0000054900",
    "position_pct": 1.59,
    "position_date": "2026-02-16",
    "previous_position_pct": 1.59,
    "change_pct": 0.0,
    "disclosure_date": "2026-02-17"
  },
  {
    "regulator": "AMF",
    "holder_name": "BLACKROCK INVESTMENT MANAGEMENT (UK) LIMITED",
    "target_company": "UBISOFT ENTERTAINMENT",
    "isin": "FR0000054470",
    "position_pct": 0.94,
    "position_date": "2026-04-08",
    "previous_position_pct": 0.94,
    "change_pct": 0.0,
    "disclosure_date": "2026-04-09"
  },
  {
    "regulator": "AMF",
    "holder_name": "BLACKROCK INVESTMENT MANAGEMENT (UK) LIMITED",
    "target_company": "VALEO",
    "isin": "FR0013176526",
    "position_pct": 1.42,
    "position_date": "2026-02-24",
    "previous_position_pct": 1.42,
    "change_pct": 0.0,
    "disclosure_date": "2026-02-25"
  },
  {
    "regulator": "AMF",
    "holder_name": "CANADA PENSION PLAN INVESTMENT BOARD",
    "target_company": "EDENRED",
    "isin": "FR0010908533",
    "position_pct": 2.4,
    "position_date": "2026-04-01",
    "previous_position_pct": 2.4,
    "change_pct": 0.0,
    "disclosure_date": "2026-04-02"
  },
  {
    "regulator": "AMF",
    "holder_name": "CANADA PENSION PLAN INVESTMENT BOARD",
    "target_company": "KLEPIERRE",
    "isin": "FR0000121964",
    "position_pct": 0.66,
    "position_date": "2026-04-08",
    "previous_position_pct": 0.66,
    "change_pct": 0.0,
    "disclosure_date": "2026-04-09"
  },
  {
    "regulator": "AMF",
    "holder_name": "CANADA PENSION PLAN INVESTMENT BOARD",
    "target_company": "NEXANS",
    "isin": "FR0000044448",
    "position_pct": 0.9,
    "position_date": "2026-03-12",
    "previous_position_pct": 0.9,
    "change_pct": 0.0,
    "disclosure_date": "2026-03-13"
  },
  {
    "regulator": "AMF",
    "holder_name": "CAPITAL FUND MANAGEMENT",
    "target_company": "AIR FRANCE-KLM",
    "isin": "FR001400J770",
    "position_pct": 0.86,
    "position_date": "2026-04-02",
    "previous_position_pct": 0.86,
    "change_pct": 0.0,
    "disclosure_date": "2026-04-03"
  },
  {
    "regulator": "AMF",
    "holder_name": "CAPITAL FUND MANAGEMENT",
    "target_company": "ATOS SE",
    "isin": "FR001400X2S4",
    "position_pct": 1.19,
    "position_date": "2026-03-06",
    "previous_position_pct": 1.19,
    "change_pct": 0.0,
    "disclosure_date": "2026-03-09"
  },
  {
    "regulator": "AMF",
    "holder_name": "CAPITAL FUND MANAGEMENT",
    "target_company": "ELIOR GROUP",
    "isin": "FR0011950732",
    "position_pct": 0.61,
    "position_date": "2026-03-30",
    "previous_position_pct": 0.61,
    "change_pct": 0.0,
    "disclosure_date": "2026-03-31"
  },
  {
    "regulator": "AMF",
    "holder_name": "CAPITAL FUND MANAGEMENT",
    "target_company": "EXOSENS",
    "isin": "FR001400Q9V2",
    "position_pct": 0.5,
    "position_date": "2026-04-02",
    "previous_position_pct": 0.5,
    "change_pct": 0.0,
    "disclosure_date": "2026-04-03"
  },
  {
    "regulator": "AMF",
    "holder_name": "CAPITAL FUND MANAGEMENT",
    "target_company": "FORVIA",
    "isin": "FR0000121147",
    "position_pct": 0.67,
    "position_date": "2026-04-01",
    "previous_position_pct": 0.67,
    "change_pct": 0.0,
    "disclosure_date": "2026-04-02"
  },
  {
    "regulator": "AMF",
    "holder_name": "CAPITAL FUND MANAGEMENT",
    "target_company": "MEDINCELL",
    "isin": "FR0004065605",
    "position_pct": 0.6,
    "position_date": "2026-03-24",
    "previous_position_pct": 0.6,
    "change_pct": 0.0,
    "disclosure_date": "2026-03-25"
  },
  {
    "regulator": "AMF",
    "holder_name": "CAPITAL FUND MANAGEMENT",
    "target_company": "SODEXO",
    "isin": "FR0000121220",
    "position_pct": 0.5,
    "position_date": "2026-04-08",
    "previous_position_pct": 0.5,
    "change_pct": 0.0,
    "disclosure_date": "2026-04-09"
  },
  {
    "regulator": "AMF",
    "holder_name": "CAPITAL FUND MANAGEMENT",
    "target_company": "VIRIDIEN",
    "isin": "FR001400PVN6",
    "position_pct": 1.3,
    "position_date": "2026-03-24",
    "previous_position_pct": 1.3,
    "change_pct": 0.0,
    "disclosure_date": "2026-03-25"
  },
  {
    "regulator": "AMF",
    "holder_name": "CITADEL ADVISORS EUROPE LIMITED",
    "target_company": "COVIVIO",
    "isin": "FR0000064578",
    "position_pct": 0.5,
    "position_date": "2023-05-19",
    "previous_position_pct": 0.5,
    "change_pct": 0.0,
    "disclosure_date": "2023-05-22"
  },
  {
    "regulator": "AMF",
    "holder_name": "CITADEL ADVISORS EUROPE LIMITED",
    "target_company": "ELIS",
    "isin": "FR0012435121",
    "position_pct": 1.7,
    "position_date": "2026-04-02",
    "previous_position_pct": 1.7,
    "change_pct": 0.0,
    "disclosure_date": "2026-04-03"
  },
  {
    "regulator": "AMF",
    "holder_name": "CITADEL ADVISORS EUROPE LIMITED",
    "target_company": "VALEO",
    "isin": "FR0013176526",
    "position_pct": 1.3,
    "position_date": "2026-04-07",
    "previous_position_pct": 1.3,
    "change_pct": 0.0,
    "disclosure_date": "2026-04-08"
  },
  {
    "regulator": "AMF",
    "holder_name": "CITADEL ADVISORS LLC",
    "target_company": "EUROAPI",
    "isin": "FR0014008VX5",
    "position_pct": 1.1,
    "position_date": "2026-03-26",
    "previous_position_pct": 1.1,
    "change_pct": 0.0,
    "disclosure_date": "2026-03-27"
  },
  {
    "regulator": "AMF",
    "holder_name": "CITADEL ADVISORS LLC",
    "target_company": "LECTRA SA",
    "isin": "FR0000065484",
    "position_pct": 0.5,
    "position_date": "2026-03-16",
    "previous_position_pct": 0.5,
    "change_pct": 0.0,
    "disclosure_date": "2026-03-17"
  },
  {
    "regulator": "AMF",
    "holder_name": "CITADEL ADVISORS LLC",
    "target_company": "NEXITY",
    "isin": "FR0010112524",
    "position_pct": 0.92,
    "position_date": "2026-03-25",
    "previous_position_pct": 0.92,
    "change_pct": 0.0,
    "disclosure_date": "2026-03-26"
  },
  {
    "regulator": "AMF",
    "holder_name": "CITADEL ADVISORS LLC",
    "target_company": "PULLUP ENTERTAINMENT",
    "isin": "FR0012419307",
    "position_pct": 0.79,
    "position_date": "2026-03-10",
    "previous_position_pct": 0.79,
    "change_pct": 0.0,
    "disclosure_date": "2026-03-11"
  },
  {
    "regulator": "AMF",
    "holder_name": "CITADEL ADVISORS LLC",
    "target_company": "QUADIENT S.A.",
    "isin": "FR0000120560",
    "position_pct": 0.58,
    "position_date": "2026-04-07",
    "previous_position_pct": 0.58,
    "change_pct": 0.0,
    "disclosure_date": "2026-04-08"
  },
  {
    "regulator": "AMF",
    "holder_name": "CITADEL ADVISORS LLC",
    "target_company": "TELEPERFORMANCE",
    "isin": "FR0000051807",
    "position_pct": 0.86,
    "position_date": "2026-04-08",
    "previous_position_pct": 0.86,
    "change_pct": 0.0,
    "disclosure_date": "2026-04-09"
  },
  {
    "regulator": "AMF",
    "holder_name": "CITADEL ADVISORS LLC",
    "target_company": "UBISOFT ENTERTAINMENT",
    "isin": "FR0000054470",
    "position_pct": 3.28,
    "position_date": "2026-04-02",
    "previous_position_pct": 3.28,
    "change_pct": 0.0,
    "disclosure_date": "2026-04-03"
  },
  {
    "regulator": "AMF",
    "holder_name": "CITADEL ADVISORS LLC",
    "target_company": "VALEO",
    "isin": "FR0013176526",
    "position_pct": 1.24,
    "position_date": "2026-04-08",
    "previous_position_pct": 1.24,
    "change_pct": 0.0,
    "disclosure_date": "2026-04-09"
  },
  {
    "regulator": "AMF",
    "holder_name": "CITADEL ADVISORS LLC",
    "target_company": "VUSIONGROUP",
    "isin": "FR0010282822",
    "position_pct": 0.69,
    "position_date": "2026-03-24",
    "previous_position_pct": 0.69,
    "change_pct": 0.0,
    "disclosure_date": "2026-03-25"
  },
  {
    "regulator": "AMF",
    "holder_name": "CITADEL SECURITIES GP LLC",
    "target_company": "CELLNOVO GROUP",
    "isin": "FR0012633360",
    "position_pct": 0.9,
    "position_date": "2019-05-03",
    "previous_position_pct": 0.9,
    "change_pct": 0.0,
    "disclosure_date": "2019-05-06"
  },
  {
    "regulator": "AMF",
    "holder_name": "CONNOR, CLARK & LUNN INVESTMENT MANAGEMENT LTD.",
    "target_company": "MERCIALYS",
    "isin": "FR0010241638",
    "position_pct": 0.6,
    "position_date": "2026-03-20",
    "previous_position_pct": 0.6,
    "change_pct": 0.0,
    "disclosure_date": "2026-03-23"
  },
  {
    "regulator": "AMF",
    "holder_name": "CREDIT INDUSTRIEL ET COMMERCIAL",
    "target_company": "VALLOUREC",
    "isin": "FR0013506730",
    "position_pct": 1.81,
    "position_date": "2025-07-11",
    "previous_position_pct": 1.81,
    "change_pct": 0.0,
    "disclosure_date": "2025-07-14"
  },
  {
    "regulator": "AMF",
    "holder_name": "D. E. SHAW & CO., L.P.",
    "target_company": "ABIVAX",
    "isin": "FR0012333284",
    "position_pct": 1.51,
    "position_date": "2026-03-03",
    "previous_position_pct": 1.51,
    "change_pct": 0.0,
    "disclosure_date": "2026-03-04"
  },
  {
    "regulator": "AMF",
    "holder_name": "D. E. SHAW & CO., L.P.",
    "target_company": "CAPGEMINI",
    "isin": "FR0000125338",
    "position_pct": 0.6,
    "position_date": "2026-03-10",
    "previous_position_pct": 0.6,
    "change_pct": 0.0,
    "disclosure_date": "2026-03-11"
  },
  {
    "regulator": "AMF",
    "holder_name": "D. E. SHAW & CO., L.P.",
    "target_company": "EDENRED",
    "isin": "FR0010908533",
    "position_pct": 0.98,
    "position_date": "2026-04-08",
    "previous_position_pct": 0.98,
    "change_pct": 0.0,
    "disclosure_date": "2026-04-09"
  },
  {
    "regulator": "AMF",
    "holder_name": "D. E. SHAW & CO., L.P.",
    "target_company": "UBISOFT ENTERTAINMENT",
    "isin": "FR0000054470",
    "position_pct": 1.96,
    "position_date": "2026-04-08",
    "previous_position_pct": 1.96,
    "change_pct": 0.0,
    "disclosure_date": "2026-04-09"
  },
  {
    "regulator": "AMF",
    "holder_name": "D. E. SHAW & CO., L.P.",
    "target_company": "VALNEVA SE",
    "isin": "FR0004056851",
    "position_pct": 0.7,
    "position_date": "2026-03-25",
    "previous_position_pct": 0.7,
    "change_pct": 0.0,
    "disclosure_date": "2026-03-26"
  },
  {
    "regulator": "AMF",
    "holder_name": "D. E. SHAW & CO., L.P.",
    "target_company": "VUSIONGROUP",
    "isin": "FR0010282822",
    "position_pct": 0.89,
    "position_date": "2026-03-23",
    "previous_position_pct": 0.89,
    "change_pct": 0.0,
    "disclosure_date": "2026-03-24"
  },
  {
    "regulator": "AMF",
    "holder_name": "D1 CAPITAL PARTNERS L.P.",
    "target_company": "PUBLICIS GROUPE SA",
    "isin": "FR0000130577",
    "position_pct": 0.59,
    "position_date": "2026-02-13",
    "previous_position_pct": 0.59,
    "change_pct": 0.0,
    "disclosure_date": "2026-02-16"
  },
  {
    "regulator": "AMF",
    "holder_name": "DAVIDSON KEMPNER EUROPEAN PARTNERS, LLP",
    "target_company": "VUSIONGROUP",
    "isin": "FR0010282822",
    "position_pct": 0.92,
    "position_date": "2026-03-03",
    "previous_position_pct": 0.92,
    "change_pct": 0.0,
    "disclosure_date": "2026-03-04"
  },
  {
    "regulator": "AMF",
    "holder_name": "ELLIOTT INVESTMENT MANAGEMENT L.P.",
    "target_company": "TOTALENERGIES SE",
    "isin": "FR0000120271",
    "position_pct": 0.91,
    "position_date": "2026-02-19",
    "previous_position_pct": 0.91,
    "change_pct": 0.0,
    "disclosure_date": "2026-02-20"
  },
  {
    "regulator": "AMF",
    "holder_name": "EMS CAPITAL LP",
    "target_company": "SOCIETE BIC",
    "isin": "FR0000120966",
    "position_pct": 0.66,
    "position_date": "2019-07-31",
    "previous_position_pct": 0.66,
    "change_pct": 0.0,
    "disclosure_date": "2019-08-02"
  },
  {
    "regulator": "AMF",
    "holder_name": "ENVESTRA CAPITAL LLP",
    "target_company": "VALEO",
    "isin": "FR0013176526",
    "position_pct": 0.73,
    "position_date": "2026-03-19",
    "previous_position_pct": 0.73,
    "change_pct": 0.0,
    "disclosure_date": "2026-03-20"
  },
  {
    "regulator": "AMF",
    "holder_name": "EXODUSPOINT CAPITAL MANAGEMENT, LP",
    "target_company": "TELEPERFORMANCE",
    "isin": "FR0000051807",
    "position_pct": 0.59,
    "position_date": "2026-04-08",
    "previous_position_pct": 0.59,
    "change_pct": 0.0,
    "disclosure_date": "2026-04-09"
  },
  {
    "regulator": "AMF",
    "holder_name": "GLADSTONE CAPITAL MANAGEMENT LLP",
    "target_company": "EDENRED",
    "isin": "FR0010908533",
    "position_pct": 0.68,
    "position_date": "2026-04-01",
    "previous_position_pct": 0.68,
    "change_pct": 0.0,
    "disclosure_date": "2026-04-02"
  },
  {
    "regulator": "AMF",
    "holder_name": "GLADSTONE CAPITAL MANAGEMENT LLP",
    "target_company": "TELEPERFORMANCE",
    "isin": "FR0000051807",
    "position_pct": 1.01,
    "position_date": "2026-03-23",
    "previous_position_pct": 1.01,
    "change_pct": 0.0,
    "disclosure_date": "2026-03-24"
  },
  {
    "regulator": "AMF",
    "holder_name": "GSA CAPITAL PARTNERS LLP",
    "target_company": "CELLECTIS",
    "isin": "FR0010425595",
    "position_pct": 0.5,
    "position_date": "2023-02-07",
    "previous_position_pct": 0.5,
    "change_pct": 0.0,
    "disclosure_date": "2023-02-08"
  },
  {
    "regulator": "AMF",
    "holder_name": "GSA CAPITAL PARTNERS LLP",
    "target_company": "EKINOPS",
    "isin": "FR0011466069",
    "position_pct": 0.5,
    "position_date": "2026-02-18",
    "previous_position_pct": 0.5,
    "change_pct": 0.0,
    "disclosure_date": "2026-02-19"
  },
  {
    "regulator": "AMF",
    "holder_name": "GSA CAPITAL PARTNERS LLP",
    "target_company": "SOLUTIONS 30 SE",
    "isin": "FR0013379484",
    "position_pct": 0.8,
    "position_date": "2026-03-30",
    "previous_position_pct": 0.8,
    "change_pct": 0.0,
    "disclosure_date": "2026-03-31"
  },
  {
    "regulator": "AMF",
    "holder_name": "GSA CAPITAL PARTNERS LLP",
    "target_company": "VALNEVA SE",
    "isin": "FR0004056851",
    "position_pct": 0.6,
    "position_date": "2026-02-06",
    "previous_position_pct": 0.6,
    "change_pct": 0.0,
    "disclosure_date": "2026-02-09"
  },
  {
    "regulator": "AMF",
    "holder_name": "GUEVOURA FUND LIMITED",
    "target_company": "VALLOUREC",
    "isin": "FR0013506730",
    "position_pct": 0.95,
    "position_date": "2021-06-29",
    "previous_position_pct": 0.95,
    "change_pct": 0.0,
    "disclosure_date": "2021-06-30"
  },
  {
    "regulator": "AMF",
    "holder_name": "HRTEU LIMITED",
    "target_company": "CLARIANE SE",
    "isin": "FR0010386334",
    "position_pct": 0.99,
    "position_date": "2024-11-22",
    "previous_position_pct": 0.99,
    "change_pct": 0.0,
    "disclosure_date": "2024-11-25"
  },
  {
    "regulator": "AMF",
    "holder_name": "Helikon Investments Limited",
    "target_company": "WORLDLINE",
    "isin": "FR0011981968",
    "position_pct": 1.51,
    "position_date": "2026-03-10",
    "previous_position_pct": 1.51,
    "change_pct": 0.0,
    "disclosure_date": "2026-03-11"
  },
  {
    "regulator": "AMF",
    "holder_name": "ILEX CAPITAL PARTNERS (UK) LLP",
    "target_company": "ACCOR",
    "isin": "FR0000120404",
    "position_pct": 0.54,
    "position_date": "2026-04-08",
    "previous_position_pct": 0.54,
    "change_pct": 0.0,
    "disclosure_date": "2026-04-09"
  },
  {
    "regulator": "AMF",
    "holder_name": "ILEX CAPITAL PARTNERS (UK) LLP",
    "target_company": "EUROFINS SCIENTIFIC SE",
    "isin": "FR0014000MR3",
    "position_pct": 0.51,
    "position_date": "2026-04-01",
    "previous_position_pct": 0.51,
    "change_pct": 0.0,
    "disclosure_date": "2026-04-02"
  },
  {
    "regulator": "AMF",
    "holder_name": "ILEX CAPITAL PARTNERS (UK) LLP",
    "target_company": "FDJ UNITED",
    "isin": "FR0013451333",
    "position_pct": 3.3,
    "position_date": "2026-03-17",
    "previous_position_pct": 3.3,
    "change_pct": 0.0,
    "disclosure_date": "2026-03-18"
  },
  {
    "regulator": "AMF",
    "holder_name": "ISABELLA CAPITAL MANAGEMENT LLP",
    "target_company": "EXAIL TECHNOLOGIES",
    "isin": "FR0000062671",
    "position_pct": 1.46,
    "position_date": "2026-04-01",
    "previous_position_pct": 1.46,
    "change_pct": 0.0,
    "disclosure_date": "2026-04-02"
  },
  {
    "regulator": "AMF",
    "holder_name": "JERICHO CAPITAL ASSET MANAGEMENT L.P.",
    "target_company": "TELEPERFORMANCE",
    "isin": "FR0000051807",
    "position_pct": 1.18,
    "position_date": "2025-06-04",
    "previous_position_pct": 1.18,
    "change_pct": 0.0,
    "disclosure_date": "2025-06-05"
  },
  {
    "regulator": "AMF",
    "holder_name": "JPMORGAN ASSET MANAGEMENT (UK) LIMITED",
    "target_company": "CLARIANE SE",
    "isin": "FR0010386334",
    "position_pct": 0.5,
    "position_date": "2025-11-11",
    "previous_position_pct": 0.5,
    "change_pct": 0.0,
    "disclosure_date": "2025-11-12"
  },
  {
    "regulator": "AMF",
    "holder_name": "JPMORGAN ASSET MANAGEMENT (UK) LIMITED",
    "target_company": "MEDINCELL",
    "isin": "FR0004065605",
    "position_pct": 0.86,
    "position_date": "2026-03-10",
    "previous_position_pct": 0.86,
    "change_pct": 0.0,
    "disclosure_date": "2026-03-11"
  },
  {
    "regulator": "AMF",
    "holder_name": "JPMORGAN ASSET MANAGEMENT (UK) LIMITED",
    "target_company": "SOITEC",
    "isin": "FR0013227113",
    "position_pct": 0.8,
    "position_date": "2026-03-23",
    "previous_position_pct": 0.8,
    "change_pct": 0.0,
    "disclosure_date": "2026-03-24"
  },
  {
    "regulator": "AMF",
    "holder_name": "JPMORGAN ASSET MANAGEMENT (UK) LIMITED",
    "target_company": "X-FAB SILICON FOUNDRIES SE",
    "isin": "BE0974310428",
    "position_pct": 1.06,
    "position_date": "2026-02-10",
    "previous_position_pct": 1.06,
    "change_pct": 0.0,
    "disclosure_date": "2026-02-11"
  },
  {
    "regulator": "AMF",
    "holder_name": "KINTBURY CAPITAL LLP",
    "target_company": "ALSTOM",
    "isin": "FR0010220475",
    "position_pct": 0.7,
    "position_date": "2026-04-08",
    "previous_position_pct": 0.7,
    "change_pct": 0.0,
    "disclosure_date": "2026-04-09"
  },
  {
    "regulator": "AMF",
    "holder_name": "KINTBURY CAPITAL LLP",
    "target_company": "CARREFOUR",
    "isin": "FR0000120172",
    "position_pct": 0.7,
    "position_date": "2026-03-05",
    "previous_position_pct": 0.7,
    "change_pct": 0.0,
    "disclosure_date": "2026-03-05"
  },
  {
    "regulator": "AMF",
    "holder_name": "KINTBURY CAPITAL LLP",
    "target_company": "RENAULT",
    "isin": "FR0000131906",
    "position_pct": 1.19,
    "position_date": "2026-03-26",
    "previous_position_pct": 1.19,
    "change_pct": 0.0,
    "disclosure_date": "2026-03-27"
  },
  {
    "regulator": "AMF",
    "holder_name": "KINTBURY CAPITAL LLP",
    "target_company": "VALEO",
    "isin": "FR0013176526",
    "position_pct": 2.89,
    "position_date": "2026-03-27",
    "previous_position_pct": 2.89,
    "change_pct": 0.0,
    "disclosure_date": "2026-03-30"
  },
  {
    "regulator": "AMF",
    "holder_name": "LMR PARTNERS LLP",
    "target_company": "ELIS",
    "isin": "FR0012435121",
    "position_pct": 0.81,
    "position_date": "2026-04-01",
    "previous_position_pct": 0.81,
    "change_pct": 0.0,
    "disclosure_date": "2026-04-02"
  },
  {
    "regulator": "AMF",
    "holder_name": "LMR PARTNERS LLP",
    "target_company": "EXAIL TECHNOLOGIES",
    "isin": "FR0000062671",
    "position_pct": 1.7,
    "position_date": "2026-03-24",
    "previous_position_pct": 1.7,
    "change_pct": 0.0,
    "disclosure_date": "2026-03-25"
  },
  {
    "regulator": "AMF",
    "holder_name": "LMR PARTNERS LLP",
    "target_company": "SPIE SA",
    "isin": "FR0012757854",
    "position_pct": 0.6,
    "position_date": "2026-04-08",
    "previous_position_pct": 0.6,
    "change_pct": 0.0,
    "disclosure_date": "2026-04-09"
  },
  {
    "regulator": "AMF",
    "holder_name": "LMR PARTNERS LLP",
    "target_company": "VALLOUREC",
    "isin": "FR0013506730",
    "position_pct": 1.91,
    "position_date": "2025-11-07",
    "previous_position_pct": 1.91,
    "change_pct": 0.0,
    "disclosure_date": "2025-11-10"
  },
  {
    "regulator": "AMF",
    "holder_name": "MARBLE BAR ASSET MANAGEMENT LLP",
    "target_company": "SOPRA STERIA GROUP",
    "isin": "FR0000050809",
    "position_pct": 1.01,
    "position_date": "2026-04-08",
    "previous_position_pct": 1.01,
    "change_pct": 0.0,
    "disclosure_date": "2026-04-09"
  },
  {
    "regulator": "AMF",
    "holder_name": "MARBLE BAR ASSET MANAGEMENT LLP",
    "target_company": "VUSIONGROUP",
    "isin": "FR0010282822",
    "position_pct": 0.53,
    "position_date": "2026-03-02",
    "previous_position_pct": 0.53,
    "change_pct": 0.0,
    "disclosure_date": "2026-03-03"
  },
  {
    "regulator": "AMF",
    "holder_name": "MARCHANT MC LTD",
    "target_company": "REMY COINTREAU",
    "isin": "FR0000130395",
    "position_pct": 0.8,
    "position_date": "2026-03-03",
    "previous_position_pct": 0.8,
    "change_pct": 0.0,
    "disclosure_date": "2026-03-04"
  },
  {
    "regulator": "AMF",
    "holder_name": "MARCHANT MC LTD",
    "target_company": "UBISOFT ENTERTAINMENT",
    "isin": "FR0000054470",
    "position_pct": 1.63,
    "position_date": "2026-03-31",
    "previous_position_pct": 1.63,
    "change_pct": 0.0,
    "disclosure_date": "2026-04-01"
  },
  {
    "regulator": "AMF",
    "holder_name": "MARCHANT MC LTD",
    "target_company": "VUSIONGROUP",
    "isin": "FR0010282822",
    "position_pct": 0.86,
    "position_date": "2026-03-31",
    "previous_position_pct": 0.86,
    "change_pct": 0.0,
    "disclosure_date": "2026-04-01"
  },
  {
    "regulator": "AMF",
    "holder_name": "MARSHALL WACE LLP",
    "target_company": "CAPITAL B",
    "isin": "FR0011053636",
    "position_pct": 1.09,
    "position_date": "2026-02-04",
    "previous_position_pct": 1.09,
    "change_pct": 0.0,
    "disclosure_date": "2026-02-05"
  },
  {
    "regulator": "AMF",
    "holder_name": "MARSHALL WACE LLP",
    "target_company": "COMPAGNIE GENERALE DES ETABLISSEMENTS MICHELIN",
    "isin": "FR001400AJ45",
    "position_pct": 0.5,
    "position_date": "2026-04-02",
    "previous_position_pct": 0.5,
    "change_pct": 0.0,
    "disclosure_date": "2026-04-07"
  },
  {
    "regulator": "AMF",
    "holder_name": "MARSHALL WACE LLP",
    "target_company": "EDENRED",
    "isin": "FR0010908533",
    "position_pct": 1.42,
    "position_date": "2026-04-08",
    "previous_position_pct": 1.42,
    "change_pct": 0.0,
    "disclosure_date": "2026-04-09"
  },
  {
    "regulator": "AMF",
    "holder_name": "MARSHALL WACE LLP",
    "target_company": "ELIOR GROUP",
    "isin": "FR0011950732",
    "position_pct": 0.97,
    "position_date": "2026-03-23",
    "previous_position_pct": 0.97,
    "change_pct": 0.0,
    "disclosure_date": "2026-03-24"
  },
  {
    "regulator": "AMF",
    "holder_name": "MARSHALL WACE LLP",
    "target_company": "EMEIS",
    "isin": "FR001400NLM4",
    "position_pct": 0.5,
    "position_date": "2026-03-20",
    "previous_position_pct": 0.5,
    "change_pct": 0.0,
    "disclosure_date": "2026-03-23"
  },
  {
    "regulator": "AMF",
    "holder_name": "MARSHALL WACE LLP",
    "target_company": "FDJ UNITED",
    "isin": "FR0013451333",
    "position_pct": 0.58,
    "position_date": "2026-03-26",
    "previous_position_pct": 0.58,
    "change_pct": 0.0,
    "disclosure_date": "2026-03-27"
  },
  {
    "regulator": "AMF",
    "holder_name": "MARSHALL WACE LLP",
    "target_company": "FORVIA",
    "isin": "FR0000121147",
    "position_pct": 1.63,
    "position_date": "2026-04-02",
    "previous_position_pct": 1.63,
    "change_pct": 0.0,
    "disclosure_date": "2026-04-07"
  },
  {
    "regulator": "AMF",
    "holder_name": "MARSHALL WACE LLP",
    "target_company": "IPSOS",
    "isin": "FR0000073298",
    "position_pct": 0.5,
    "position_date": "2026-03-31",
    "previous_position_pct": 0.5,
    "change_pct": 0.0,
    "disclosure_date": "2026-04-01"
  },
  {
    "regulator": "AMF",
    "holder_name": "MARSHALL WACE LLP",
    "target_company": "NEXITY",
    "isin": "FR0010112524",
    "position_pct": 1.09,
    "position_date": "2026-03-30",
    "previous_position_pct": 1.09,
    "change_pct": 0.0,
    "disclosure_date": "2026-03-31"
  },
  {
    "regulator": "AMF",
    "holder_name": "MARSHALL WACE LLP",
    "target_company": "PUBLICIS GROUPE SA",
    "isin": "FR0000130577",
    "position_pct": 1.49,
    "position_date": "2026-04-02",
    "previous_position_pct": 1.49,
    "change_pct": 0.0,
    "disclosure_date": "2026-04-07"
  },
  {
    "regulator": "AMF",
    "holder_name": "MARSHALL WACE LLP",
    "target_company": "RENAULT",
    "isin": "FR0000131906",
    "position_pct": 1.2,
    "position_date": "2026-04-08",
    "previous_position_pct": 1.2,
    "change_pct": 0.0,
    "disclosure_date": "2026-04-09"
  },
  {
    "regulator": "AMF",
    "holder_name": "MARSHALL WACE LLP",
    "target_company": "SODEXO",
    "isin": "FR0000121220",
    "position_pct": 0.69,
    "position_date": "2026-04-02",
    "previous_position_pct": 0.69,
    "change_pct": 0.0,
    "disclosure_date": "2026-04-07"
  },
  {
    "regulator": "AMF",
    "holder_name": "MARSHALL WACE LLP",
    "target_company": "TELEPERFORMANCE",
    "isin": "FR0000051807",
    "position_pct": 2.47,
    "position_date": "2026-03-31",
    "previous_position_pct": 2.47,
    "change_pct": 0.0,
    "disclosure_date": "2026-04-01"
  },
  {
    "regulator": "AMF",
    "holder_name": "MARSHALL WACE LLP",
    "target_company": "UBISOFT ENTERTAINMENT",
    "isin": "FR0000054470",
    "position_pct": 2.3,
    "position_date": "2026-04-08",
    "previous_position_pct": 2.3,
    "change_pct": 0.0,
    "disclosure_date": "2026-04-09"
  },
  {
    "regulator": "AMF",
    "holder_name": "MARSHALL WACE LLP",
    "target_company": "VALEO",
    "isin": "FR0013176526",
    "position_pct": 2.72,
    "position_date": "2026-04-01",
    "previous_position_pct": 2.72,
    "change_pct": 0.0,
    "disclosure_date": "2026-04-02"
  },
  {
    "regulator": "AMF",
    "holder_name": "MARSHALL WACE LLP",
    "target_company": "VIRIDIEN",
    "isin": "FR001400PVN6",
    "position_pct": 0.53,
    "position_date": "2026-04-08",
    "previous_position_pct": 0.53,
    "change_pct": 0.0,
    "disclosure_date": "2026-04-09"
  },
  {
    "regulator": "AMF",
    "holder_name": "MILLENNIUM CAPITAL PARTNERS LLP",
    "target_company": "ATOS SE",
    "isin": "FR001400X2S4",
    "position_pct": 0.5,
    "position_date": "2026-03-27",
    "previous_position_pct": 0.5,
    "change_pct": 0.0,
    "disclosure_date": "2026-03-30"
  },
  {
    "regulator": "AMF",
    "holder_name": "MILLENNIUM CAPITAL PARTNERS LLP",
    "target_company": "CASINO GUICHARD-PERRACHON",
    "isin": "FR001400OKR3",
    "position_pct": 1.31,
    "position_date": "2026-02-05",
    "previous_position_pct": 1.31,
    "change_pct": 0.0,
    "disclosure_date": "2026-02-06"
  },
  {
    "regulator": "AMF",
    "holder_name": "MILLENNIUM CAPITAL PARTNERS LLP",
    "target_company": "FORVIA",
    "isin": "FR0000121147",
    "position_pct": 1.2,
    "position_date": "2026-04-02",
    "previous_position_pct": 1.2,
    "change_pct": 0.0,
    "disclosure_date": "2026-04-03"
  },
  {
    "regulator": "AMF",
    "holder_name": "MILLENNIUM CAPITAL PARTNERS LLP",
    "target_company": "UBISOFT ENTERTAINMENT",
    "isin": "FR0000054470",
    "position_pct": 0.51,
    "position_date": "2026-04-08",
    "previous_position_pct": 0.51,
    "change_pct": 0.0,
    "disclosure_date": "2026-04-09"
  },
  {
    "regulator": "AMF",
    "holder_name": "MILLENNIUM CAPITAL PARTNERS LLP",
    "target_company": "VALEO",
    "isin": "FR0013176526",
    "position_pct": 1.39,
    "position_date": "2026-04-08",
    "previous_position_pct": 1.39,
    "change_pct": 0.0,
    "disclosure_date": "2026-04-09"
  },
  {
    "regulator": "AMF",
    "holder_name": "MILLENNIUM INTERNATIONAL MANAGEMENT LP",
    "target_company": "ELIOR GROUP",
    "isin": "FR0011950732",
    "position_pct": 0.52,
    "position_date": "2026-04-08",
    "previous_position_pct": 0.52,
    "change_pct": 0.0,
    "disclosure_date": "2026-04-09"
  },
  {
    "regulator": "AMF",
    "holder_name": "MILLENNIUM INTERNATIONAL MANAGEMENT LP",
    "target_company": "EUTELSAT COMMUNICATIONS",
    "isin": "FR0010221234",
    "position_pct": 0.98,
    "position_date": "2020-05-28",
    "previous_position_pct": 0.98,
    "change_pct": 0.0,
    "disclosure_date": "2020-05-29"
  },
  {
    "regulator": "AMF",
    "holder_name": "MILLENNIUM INTERNATIONAL MANAGEMENT LP",
    "target_company": "EXOSENS",
    "isin": "FR001400Q9V2",
    "position_pct": 0.56,
    "position_date": "2026-04-01",
    "previous_position_pct": 0.56,
    "change_pct": 0.0,
    "disclosure_date": "2026-04-02"
  },
  {
    "regulator": "AMF",
    "holder_name": "MILLENNIUM INTERNATIONAL MANAGEMENT LP",
    "target_company": "ICADE",
    "isin": "FR0000035081",
    "position_pct": 0.5,
    "position_date": "2026-02-16",
    "previous_position_pct": 0.5,
    "change_pct": 0.0,
    "disclosure_date": "2026-02-17"
  },
  {
    "regulator": "AMF",
    "holder_name": "MILLENNIUM INTERNATIONAL MANAGEMENT LP",
    "target_company": "MEDINCELL",
    "isin": "FR0004065605",
    "position_pct": 0.5,
    "position_date": "2026-03-12",
    "previous_position_pct": 0.5,
    "change_pct": 0.0,
    "disclosure_date": "2026-03-13"
  },
  {
    "regulator": "AMF",
    "holder_name": "MILLENNIUM INTERNATIONAL MANAGEMENT LP",
    "target_company": "TELEPERFORMANCE",
    "isin": "FR0000051807",
    "position_pct": 0.7,
    "position_date": "2026-04-08",
    "previous_position_pct": 0.7,
    "change_pct": 0.0,
    "disclosure_date": "2026-04-09"
  },
  {
    "regulator": "AMF",
    "holder_name": "MILLENNIUM INTERNATIONAL MANAGEMENT LP",
    "target_company": "VALEO",
    "isin": "FR0013176526",
    "position_pct": 1.2,
    "position_date": "2026-03-13",
    "previous_position_pct": 1.2,
    "change_pct": 0.0,
    "disclosure_date": "2026-03-16"
  },
  {
    "regulator": "AMF",
    "holder_name": "MILLENNIUM INTERNATIONAL MANAGEMENT LP",
    "target_company": "VIRIDIEN",
    "isin": "FR001400PVN6",
    "position_pct": 0.91,
    "position_date": "2026-04-02",
    "previous_position_pct": 0.91,
    "change_pct": 0.0,
    "disclosure_date": "2026-04-03"
  },
  {
    "regulator": "AMF",
    "holder_name": "MIRABELLA FINANCIAL SERVICES LLP",
    "target_company": "VIRIDIEN",
    "isin": "FR001400PVN6",
    "position_pct": 0.57,
    "position_date": "2025-01-30",
    "previous_position_pct": 0.57,
    "change_pct": 0.0,
    "disclosure_date": "2025-01-31"
  },
  {
    "regulator": "AMF",
    "holder_name": "MIRABELLA FINANCIAL SERVICES LLP",
    "target_company": "VUSIONGROUP",
    "isin": "FR0010282822",
    "position_pct": 0.51,
    "position_date": "2026-03-05",
    "previous_position_pct": 0.51,
    "change_pct": 0.0,
    "disclosure_date": "2026-03-06"
  },
  {
    "regulator": "AMF",
    "holder_name": "NATIXIS",
    "target_company": "INGENICO GROUP",
    "isin": "FR0000125346",
    "position_pct": 0.59,
    "position_date": "2014-12-12",
    "previous_position_pct": 0.59,
    "change_pct": 0.0,
    "disclosure_date": "2014-12-15"
  },
  {
    "regulator": "AMF",
    "holder_name": "NATIXIS",
    "target_company": "VALLOUREC",
    "isin": "FR0013506730",
    "position_pct": 4.04,
    "position_date": "2026-04-01",
    "previous_position_pct": 4.04,
    "change_pct": 0.0,
    "disclosure_date": "2026-04-02"
  },
  {
    "regulator": "AMF",
    "holder_name": "NUMERIC INVESTORS LLC",
    "target_company": "REMY COINTREAU",
    "isin": "FR0000130395",
    "position_pct": 0.8,
    "position_date": "2026-04-02",
    "previous_position_pct": 0.8,
    "change_pct": 0.0,
    "disclosure_date": "2026-04-07"
  },
  {
    "regulator": "AMF",
    "holder_name": "NUMERIC INVESTORS LLC",
    "target_company": "SOITEC",
    "isin": "FR0013227113",
    "position_pct": 0.79,
    "position_date": "2026-04-08",
    "previous_position_pct": 0.79,
    "change_pct": 0.0,
    "disclosure_date": "2026-04-09"
  },
  {
    "regulator": "AMF",
    "holder_name": "PDT PARTNERS, LLC",
    "target_company": "FDJ UNITED",
    "isin": "FR0013451333",
    "position_pct": 0.59,
    "position_date": "2026-02-24",
    "previous_position_pct": 0.59,
    "change_pct": 0.0,
    "disclosure_date": "2026-02-25"
  },
  {
    "regulator": "AMF",
    "holder_name": "PERTENTO PARTNERS LLP",
    "target_company": "SES",
    "isin": "LU0088087324",
    "position_pct": 0.5,
    "position_date": "2024-11-05",
    "previous_position_pct": 0.5,
    "change_pct": 0.0,
    "disclosure_date": "2024-11-06"
  },
  {
    "regulator": "AMF",
    "holder_name": "PERTENTO PARTNERS LLP",
    "target_company": "VUSIONGROUP",
    "isin": "FR0010282822",
    "position_pct": 1.05,
    "position_date": "2026-03-09",
    "previous_position_pct": 1.05,
    "change_pct": 0.0,
    "disclosure_date": "2026-03-10"
  },
  {
    "regulator": "AMF",
    "holder_name": "POINT72 ASSET MANAGEMENT, L.P.",
    "target_company": "TELEPERFORMANCE",
    "isin": "FR0000051807",
    "position_pct": 1.89,
    "position_date": "2026-04-07",
    "previous_position_pct": 1.89,
    "change_pct": 0.0,
    "disclosure_date": "2026-04-08"
  },
  {
    "regulator": "AMF",
    "holder_name": "POINT72 EUROPE (LONDON) LLP",
    "target_company": "FDJ UNITED",
    "isin": "FR0013451333",
    "position_pct": 0.5,
    "position_date": "2026-03-23",
    "previous_position_pct": 0.5,
    "change_pct": 0.0,
    "disclosure_date": "2026-03-24"
  },
  {
    "regulator": "AMF",
    "holder_name": "PUBLIC EQUITY PARTNERS MANAGEMENT, L.P.",
    "target_company": "BOURBON CORPORATION",
    "isin": "FR0004548873",
    "position_pct": 1.35,
    "position_date": "2019-09-19",
    "previous_position_pct": 1.35,
    "change_pct": 0.0,
    "disclosure_date": "2019-09-20"
  },
  {
    "regulator": "AMF",
    "holder_name": "QUBE RESEARCH & TECHNOLOGIES LIMITED",
    "target_company": "ABIVAX",
    "isin": "FR0012333284",
    "position_pct": 0.79,
    "position_date": "2026-03-26",
    "previous_position_pct": 0.79,
    "change_pct": 0.0,
    "disclosure_date": "2026-03-27"
  },
  {
    "regulator": "AMF",
    "holder_name": "QUBE RESEARCH & TECHNOLOGIES LIMITED",
    "target_company": "CAPITAL B",
    "isin": "FR0011053636",
    "position_pct": 0.99,
    "position_date": "2026-04-08",
    "previous_position_pct": 0.99,
    "change_pct": 0.0,
    "disclosure_date": "2026-04-09"
  },
  {
    "regulator": "AMF",
    "holder_name": "QUBE RESEARCH & TECHNOLOGIES LIMITED",
    "target_company": "EUTELSAT COMMUNICATIONS",
    "isin": "FR0010221234",
    "position_pct": 1.39,
    "position_date": "2026-04-07",
    "previous_position_pct": 1.39,
    "change_pct": 0.0,
    "disclosure_date": "2026-04-08"
  },
  {
    "regulator": "AMF",
    "holder_name": "QUBE RESEARCH & TECHNOLOGIES LIMITED",
    "target_company": "EXAIL TECHNOLOGIES",
    "isin": "FR0000062671",
    "position_pct": 1.84,
    "position_date": "2026-03-26",
    "previous_position_pct": 1.84,
    "change_pct": 0.0,
    "disclosure_date": "2026-03-27"
  },
  {
    "regulator": "AMF",
    "holder_name": "QUBE RESEARCH & TECHNOLOGIES LIMITED",
    "target_company": "GENFIT",
    "isin": "FR0004163111",
    "position_pct": 0.68,
    "position_date": "2026-04-01",
    "previous_position_pct": 0.68,
    "change_pct": 0.0,
    "disclosure_date": "2026-04-02"
  },
  {
    "regulator": "AMF",
    "holder_name": "QUBE RESEARCH & TECHNOLOGIES LIMITED",
    "target_company": "ICADE",
    "isin": "FR0000035081",
    "position_pct": 0.8,
    "position_date": "2026-03-05",
    "previous_position_pct": 0.8,
    "change_pct": 0.0,
    "disclosure_date": "2026-03-06"
  },
  {
    "regulator": "AMF",
    "holder_name": "QUBE RESEARCH & TECHNOLOGIES LIMITED",
    "target_company": "METROPOLE TELEVISION",
    "isin": "FR0000053225",
    "position_pct": 0.5,
    "position_date": "2026-03-31",
    "previous_position_pct": 0.5,
    "change_pct": 0.0,
    "disclosure_date": "2026-04-01"
  },
  {
    "regulator": "AMF",
    "holder_name": "SAMLYN CAPITAL, LLC",
    "target_company": "EDENRED",
    "isin": "FR0010908533",
    "position_pct": 0.9,
    "position_date": "2026-03-06",
    "previous_position_pct": 0.9,
    "change_pct": 0.0,
    "disclosure_date": "2026-03-09"
  },
  {
    "regulator": "AMF",
    "holder_name": "SCULPTOR CAPITAL MANAGEMENT EUROPE LIMITED",
    "target_company": "EXAIL TECHNOLOGIES",
    "isin": "FR0000062671",
    "position_pct": 0.82,
    "position_date": "2026-04-01",
    "previous_position_pct": 0.82,
    "change_pct": 0.0,
    "disclosure_date": "2026-04-02"
  },
  {
    "regulator": "AMF",
    "holder_name": "SIH PARTNERS LLLP",
    "target_company": "UBISOFT ENTERTAINMENT",
    "isin": "FR0000054470",
    "position_pct": 1.6,
    "position_date": "2026-03-31",
    "previous_position_pct": 1.6,
    "change_pct": 0.0,
    "disclosure_date": "2026-04-01"
  },
  {
    "regulator": "AMF",
    "holder_name": "SQUAREPOINT OPS LLC",
    "target_company": "EDENRED",
    "isin": "FR0010908533",
    "position_pct": 0.51,
    "position_date": "2026-04-08",
    "previous_position_pct": 0.51,
    "change_pct": 0.0,
    "disclosure_date": "2026-04-09"
  },
  {
    "regulator": "AMF",
    "holder_name": "SQUAREPOINT OPS LLC",
    "target_company": "SODEXO",
    "isin": "FR0000121220",
    "position_pct": 0.8,
    "position_date": "2026-02-05",
    "previous_position_pct": 0.8,
    "change_pct": 0.0,
    "disclosure_date": "2026-02-06"
  },
  {
    "regulator": "AMF",
    "holder_name": "SQUAREPOINT OPS LLC",
    "target_company": "TELEPERFORMANCE",
    "isin": "FR0000051807",
    "position_pct": 1.24,
    "position_date": "2026-04-08",
    "previous_position_pct": 1.24,
    "change_pct": 0.0,
    "disclosure_date": "2026-04-09"
  },
  {
    "regulator": "AMF",
    "holder_name": "STEADFAST CAPITAL MANAGEMENT LP",
    "target_company": "PUBLICIS GROUPE SA",
    "isin": "FR0000130577",
    "position_pct": 0.57,
    "position_date": "2020-03-16",
    "previous_position_pct": 0.57,
    "change_pct": 0.0,
    "disclosure_date": "2020-03-17"
  },
  {
    "regulator": "AMF",
    "holder_name": "SYSTEMATICA INVESTMENTS LIMITED",
    "target_company": "UBISOFT ENTERTAINMENT",
    "isin": "FR0000054470",
    "position_pct": 0.59,
    "position_date": "2026-04-02",
    "previous_position_pct": 0.59,
    "change_pct": 0.0,
    "disclosure_date": "2026-04-03"
  },
  {
    "regulator": "AMF",
    "holder_name": "SurgoCap Partners LP",
    "target_company": "EDENRED",
    "isin": "FR0010908533",
    "position_pct": 0.66,
    "position_date": "2025-12-30",
    "previous_position_pct": 0.66,
    "change_pct": 0.0,
    "disclosure_date": "2025-12-31"
  },
  {
    "regulator": "AMF",
    "holder_name": "TAGES CAPITAL LLP",
    "target_company": "SOLUTIONS 30 SE",
    "isin": "FR0013379484",
    "position_pct": 0.63,
    "position_date": "2025-12-18",
    "previous_position_pct": 0.63,
    "change_pct": 0.0,
    "disclosure_date": "2025-12-19"
  },
  {
    "regulator": "AMF",
    "holder_name": "TWO SIGMA INVESTMENTS, LP",
    "target_company": "ACCOR",
    "isin": "FR0000120404",
    "position_pct": 0.59,
    "position_date": "2026-03-30",
    "previous_position_pct": 0.59,
    "change_pct": 0.0,
    "disclosure_date": "2026-03-31"
  },
  {
    "regulator": "AMF",
    "holder_name": "TWO SIGMA INVESTMENTS, LP",
    "target_company": "EDENRED",
    "isin": "FR0010908533",
    "position_pct": 1.43,
    "position_date": "2026-03-26",
    "previous_position_pct": 1.43,
    "change_pct": 0.0,
    "disclosure_date": "2026-03-27"
  },
  {
    "regulator": "AMF",
    "holder_name": "TWO SIGMA INVESTMENTS, LP",
    "target_company": "FDJ UNITED",
    "isin": "FR0013451333",
    "position_pct": 0.69,
    "position_date": "2026-04-02",
    "previous_position_pct": 0.69,
    "change_pct": 0.0,
    "disclosure_date": "2026-04-03"
  },
  {
    "regulator": "AMF",
    "holder_name": "TWO SIGMA INVESTMENTS, LP",
    "target_company": "REXEL",
    "isin": "FR0010451203",
    "position_pct": 0.69,
    "position_date": "2026-03-04",
    "previous_position_pct": 0.69,
    "change_pct": 0.0,
    "disclosure_date": "2026-03-05"
  },
  {
    "regulator": "AMF",
    "holder_name": "TWO SIGMA INVESTMENTS, LP",
    "target_company": "SODEXO",
    "isin": "FR0000121220",
    "position_pct": 0.5,
    "position_date": "2026-02-10",
    "previous_position_pct": 0.5,
    "change_pct": 0.0,
    "disclosure_date": "2026-02-11"
  },
  {
    "regulator": "AMF",
    "holder_name": "TWO SIGMA INVESTMENTS, LP",
    "target_company": "SOITEC",
    "isin": "FR0013227113",
    "position_pct": 0.66,
    "position_date": "2026-04-08",
    "previous_position_pct": 0.66,
    "change_pct": 0.0,
    "disclosure_date": "2026-04-09"
  },
  {
    "regulator": "AMF",
    "holder_name": "TWO SIGMA INVESTMENTS, LP",
    "target_company": "TELEPERFORMANCE",
    "isin": "FR0000051807",
    "position_pct": 0.71,
    "position_date": "2026-03-30",
    "previous_position_pct": 0.71,
    "change_pct": 0.0,
    "disclosure_date": "2026-03-31"
  },
  {
    "regulator": "AMF",
    "holder_name": "TWO SIGMA INVESTMENTS, LP",
    "target_company": "VUSIONGROUP",
    "isin": "FR0010282822",
    "position_pct": 0.7,
    "position_date": "2026-03-12",
    "previous_position_pct": 0.7,
    "change_pct": 0.0,
    "disclosure_date": "2026-03-13"
  },
  {
    "regulator": "AMF",
    "holder_name": "VOLEON CAPITAL MANAGEMENT LP",
    "target_company": "2CRSI",
    "isin": "FR0013341781",
    "position_pct": 2.32,
    "position_date": "2026-04-07",
    "previous_position_pct": 2.32,
    "change_pct": 0.0,
    "disclosure_date": "2026-04-08"
  },
  {
    "regulator": "AMF",
    "holder_name": "VOLEON CAPITAL MANAGEMENT LP",
    "target_company": "DBV TECHNOLOGIES",
    "isin": "FR0010417345",
    "position_pct": 0.8,
    "position_date": "2026-04-01",
    "previous_position_pct": 0.8,
    "change_pct": 0.0,
    "disclosure_date": "2026-04-02"
  },
  {
    "regulator": "AMF",
    "holder_name": "VOLEON CAPITAL MANAGEMENT LP",
    "target_company": "EDENRED",
    "isin": "FR0010908533",
    "position_pct": 0.74,
    "position_date": "2026-03-26",
    "previous_position_pct": 0.74,
    "change_pct": 0.0,
    "disclosure_date": "2026-03-27"
  },
  {
    "regulator": "AMF",
    "holder_name": "VOLEON CAPITAL MANAGEMENT LP",
    "target_company": "MEDIAN TECHNOLOGIES",
    "isin": "FR0011049824",
    "position_pct": 0.68,
    "position_date": "2026-04-01",
    "previous_position_pct": 0.68,
    "change_pct": 0.0,
    "disclosure_date": "2026-04-02"
  },
  {
    "regulator": "AMF",
    "holder_name": "VOLEON CAPITAL MANAGEMENT LP",
    "target_company": "TELEPERFORMANCE",
    "isin": "FR0000051807",
    "position_pct": 0.58,
    "position_date": "2026-03-19",
    "previous_position_pct": 0.58,
    "change_pct": 0.0,
    "disclosure_date": "2026-03-20"
  },
  {
    "regulator": "AMF",
    "holder_name": "WALLEYE CAPITAL (UK) LIMITED",
    "target_company": "EXAIL TECHNOLOGIES",
    "isin": "FR0000062671",
    "position_pct": 0.53,
    "position_date": "2026-03-18",
    "previous_position_pct": 0.53,
    "change_pct": 0.0,
    "disclosure_date": "2026-03-19"
  },
  {
    "regulator": "AMF",
    "holder_name": "WELLINGTON MANAGEMENT INTERNATIONAL LIMITED",
    "target_company": "ICADE",
    "isin": "FR0000035081",
    "position_pct": 0.75,
    "position_date": "2026-04-08",
    "previous_position_pct": 0.75,
    "change_pct": 0.0,
    "disclosure_date": "2026-04-09"
  },
  {
    "regulator": "AMF",
    "holder_name": "WHITEBOX ADVISORS LLC",
    "target_company": "EXAIL TECHNOLOGIES",
    "isin": "FR0000062671",
    "position_pct": 1.13,
    "position_date": "2026-03-10",
    "previous_position_pct": 1.13,
    "change_pct": 0.0,
    "disclosure_date": "2026-03-11"
  },
  {
    "regulator": "AMF",
    "holder_name": "WINTON CAPITAL MANAGEMENT LIMITED",
    "target_company": "NEXITY",
    "isin": "FR0010112524",
    "position_pct": 0.5,
    "position_date": "2026-03-13",
    "previous_position_pct": 0.5,
    "change_pct": 0.0,
    "disclosure_date": "2026-03-16"
  },
  {
    "regulator": "AMF",
    "holder_name": "WORLDQUANT, LLC",
    "target_company": "SOLUTIONS 30 SE",
    "isin": "FR0013379484",
    "position_pct": 0.53,
    "position_date": "2026-04-07",
    "previous_position_pct": 0.53,
    "change_pct": 0.0,
    "disclosure_date": "2026-04-08"
  },
  {
    "regulator": "AMF",
    "holder_name": "Walleye Capital LLC",
    "target_company": "AIR FRANCE-KLM",
    "isin": "FR001400J770",
    "position_pct": 1.2,
    "position_date": "2026-04-08",
    "previous_position_pct": 1.2,
    "change_pct": 0.0,
    "disclosure_date": "2026-04-09"
  },
  {
    "regulator": "AMF",
    "holder_name": "Walleye Capital LLC",
    "target_company": "TELEPERFORMANCE",
    "isin": "FR0000051807",
    "position_pct": 0.58,
    "position_date": "2026-04-08",
    "previous_position_pct": 0.58,
    "change_pct": 0.0,
    "disclosure_date": "2026-04-09"
  }
]